Workbook

Sheet Master Question Bank
A1: QuestionID | B1: QuestionText | C1: SoftControl | D1: Response | E1: Score Scale | F1: Score_100
A2: Q001 | B2: I believe that my Leaders and seniors are positive role models when it comes to successfully managing all potential risks | C2: Role Modelling | D2: Disagree | E2: =IF(tblQuestions[[#This Row],[Response]]="","",VALUE(CHOOSE(MATCH(tblQuestions[[#This Row],[Response]],{"Strongly Agree","Agree","Neutral","Disagree","Strongly Disagree"},0),5,4,3,2,1))) -> 2 | F2: =IF(tblQuestions[[#This Row],[Score Scale]]="","",tblQuestions[[#This Row],[Score Scale]]*20) -> 40
A3: Q002 | B3: All the executives set the right ‘tone at the top’ on the importance of managing all potential risks. | C3: Role Modelling | D3: Strongly Agree | E3: =IF(tblQuestions[[#This Row],[Response]]="","",VALUE(CHOOSE(MATCH(tblQuestions[[#This Row],[Response]],{"Strongly Agree","Agree","Neutral","Disagree","Strongly Disagree"},0),5,4,3,2,1))) -> 5 | F3: =IF(tblQuestions[[#This Row],[Score Scale]]="","",tblQuestions[[#This Row],[Score Scale]]*20) -> 100
A4: Q003 | B4: All the seniors encourage employees to identify, escalate and report all material potential risks in a timely manner | C4: Role Modelling | D4: Agree | E4: =IF(tblQuestions[[#This Row],[Response]]="","",VALUE(CHOOSE(MATCH(tblQuestions[[#This Row],[Response]],{"Strongly Agree","Agree","Neutral","Disagree","Strongly Disagree"},0),5,4,3,2,1))) -> 4 | F4: =IF(tblQuestions[[#This Row],[Score Scale]]="","",tblQuestions[[#This Row],[Score Scale]]*20) -> 80
A5: Q004 | B5: When decisions are made by leaders, potential and long-term implications are usually considered. | C5: Role Modelling | D5: Disagree | E5: =IF(tblQuestions[[#This Row],[Response]]="","",VALUE(CHOOSE(MATCH(tblQuestions[[#This Row],[Response]],{"Strongly Agree","Agree","Neutral","Disagree","Strongly Disagree"},0),5,4,3,2,1))) -> 2 | F5: =IF(tblQuestions[[#This Row],[Score Scale]]="","",tblQuestions[[#This Row],[Score Scale]]*20) -> 40
A6: Q005 | B6: In a Team or with leaders we can discuss openly when results fall short,and expectations aren’t met. | C6: Discussability | D6: Agree | E6: =IF(tblQuestions[[#This Row],[Response]]="","",VALUE(CHOOSE(MATCH(tblQuestions[[#This Row],[Response]],{"Strongly Agree","Agree","Neutral","Disagree","Strongly Disagree"},0),5,4,3,2,1))) -> 4 | F6: =IF(tblQuestions[[#This Row],[Score Scale]]="","",tblQuestions[[#This Row],[Score Scale]]*20) -> 80
A7: Q006 | B7: People can seek advice if they have questions about managing tasks or risks in the team. | C7: Discussability | D7: Disagree | E7: =IF(tblQuestions[[#This Row],[Response]]="","",VALUE(CHOOSE(MATCH(tblQuestions[[#This Row],[Response]],{"Strongly Agree","Agree","Neutral","Disagree","Strongly Disagree"},0),5,4,3,2,1))) -> 2 | F7: =IF(tblQuestions[[#This Row],[Score Scale]]="","",tblQuestions[[#This Row],[Score Scale]]*20) -> 40
A8: Q007 | B8: People feel comfortable sharing their opinion on work and risk management. | C8: Discussability | D8: Neutral | E8: =IF(tblQuestions[[#This Row],[Response]]="","",VALUE(CHOOSE(MATCH(tblQuestions[[#This Row],[Response]],{"Strongly Agree","Agree","Neutral","Disagree","Strongly Disagree"},0),5,4,3,2,1))) -> 3 | F8: =IF(tblQuestions[[#This Row],[Score Scale]]="","",tblQuestions[[#This Row],[Score Scale]]*20) -> 60
A9: Q008 | B9: Within my team or department people feel comfortable to report risk management dillemas or if something goes wrong. | C9: Discussability | D9: Strongly Disagree | E9: =IF(tblQuestions[[#This Row],[Response]]="","",VALUE(CHOOSE(MATCH(tblQuestions[[#This Row],[Response]],{"Strongly Agree","Agree","Neutral","Disagree","Strongly Disagree"},0),5,4,3,2,1))) -> 1 | F9: =IF(tblQuestions[[#This Row],[Score Scale]]="","",tblQuestions[[#This Row],[Score Scale]]*20) -> 20
A10: Q009 | B10: The amount of training in risk management I have received to help me manage risk in my job is sufficient. | C10: Achievability | D10: Strongly Disagree | E10: =IF(tblQuestions[[#This Row],[Response]]="","",VALUE(CHOOSE(MATCH(tblQuestions[[#This Row],[Response]],{"Strongly Agree","Agree","Neutral","Disagree","Strongly Disagree"},0),5,4,3,2,1))) -> 1 | F10: =IF(tblQuestions[[#This Row],[Score Scale]]="","",tblQuestions[[#This Row],[Score Scale]]*20) -> 20
A11: Q010 | B11: Within my team or department people have enough time and resources to do their job without taking unacceptable risks | C11: Achievability | D11: Disagree | E11: =IF(tblQuestions[[#This Row],[Response]]="","",VALUE(CHOOSE(MATCH(tblQuestions[[#This Row],[Response]],{"Strongly Agree","Agree","Neutral","Disagree","Strongly Disagree"},0),5,4,3,2,1))) -> 2 | F11: =IF(tblQuestions[[#This Row],[Score Scale]]="","",tblQuestions[[#This Row],[Score Scale]]*20) -> 40
A12: Q011 | B12: People set targets that are achievable without compromising risk management policies, guidelines and procedures. | C12: Achievability | D12: Neutral | E12: =IF(tblQuestions[[#This Row],[Response]]="","",VALUE(CHOOSE(MATCH(tblQuestions[[#This Row],[Response]],{"Strongly Agree","Agree","Neutral","Disagree","Strongly Disagree"},0),5,4,3,2,1))) -> 3 | F12: =IF(tblQuestions[[#This Row],[Score Scale]]="","",tblQuestions[[#This Row],[Score Scale]]*20) -> 60
A13: Q012 | B13: People visibly consider potential risks when making strategic decisions | C13: Achievability | D13: Neutral | E13: =IF(tblQuestions[[#This Row],[Response]]="","",VALUE(CHOOSE(MATCH(tblQuestions[[#This Row],[Response]],{"Strongly Agree","Agree","Neutral","Disagree","Strongly Disagree"},0),5,4,3,2,1))) -> 3 | F13: =IF(tblQuestions[[#This Row],[Score Scale]]="","",tblQuestions[[#This Row],[Score Scale]]*20) -> 60
... A33: Q032 | B33: Within my team at workplace, people are receptive to criticism on their own conduct. | C33: Call someone to account | D33: Agree | E33: =IF(tblQuestions[[#This Row],[Response]]="","",VALUE(CHOOSE(MATCH(tblQuestions[[#This Row],[Response]],{"Strongly Agree","Agree","Neutral","Disagree","Strongly Disagree"},0),5,4,3,2,1))) -> 4 | F33: =IF(tblQuestions[[#This Row],[Score Scale]]="","",tblQuestions[[#This Row],[Score Scale]]*20) -> 80
A34: Q033 | B34: Did you experienced or witnessed a violation of company values or the Code of Conduct within the last twelve months | F34: =IF(tblQuestions[[#This Row],[Score Scale]]="","",tblQuestions[[#This Row],[Score Scale]]*20)
A35: Q034 | B35: To whom would you like to report undesired behavior instances happening in you organization | F35: =IF(tblQuestions[[#This Row],[Score Scale]]="","",tblQuestions[[#This Row],[Score Scale]]*20)

Sheet FinalQuestions
A1: QuestionID | B1: QuestionText | C1: SoftControl | D1: Dimensions | E1: What it means to your organization | F1: Business Impact | G1: High Risk Statements | H1: Med Risk Statements | I1: Low Risk Statements | J1: Flagged
A2: Q001 | B2: I believe that my leaders and senior managers consistently act as positive role models, also when they are under time pressure or facing difficult trade‑offs. | C2: Role Modelling | D2: Leadership Example‑Setting in Risk Management | E2: It reflects how consistently leaders demonstrate risk‑aware behavior through their decisions and day‑to‑day actions. | F2: When this is low, employees receive mixed signals about expected behavior, leading to inconsistency, reduced trust in leadership, and weaker cultural alignment. | G2: Leaders are not consistently demonstrating expected risk‑aware behavior. This creates confusion within teams about what is acceptable and weakens trust in leadership decisions. | H2: Leadership intent is understood, but behaviors are not consistently demonstrated across levels. This may lead to pockets of inconsistency and uneven culture adoption. | I2: Leaders consistently role‑model strong risk‑aware behaviors. This sets clear expectations and strongly reinforces the desired culture across the organization. | J2: No
A3: Q002 | B3: Leaders openly emphasize the importance of doing things the right way, even under time pressure | C3: Role Modelling | D3: Executive Commitment to Risk Culture | E3: Shows how visibly senior leadership prioritizes and reinforces a strong risk culture. | F3: Low commitment reduces the credibility of risk initiatives, slows cultural adoption, and causes employees to deprioritize risk considerations. | G3: Senior leadership support for risk culture is perceived as weak or inconsistent. As a result, employees deprioritize risk considerations in daily decisions. | H3: Executives communicate commitment to risk culture, but reinforcement is not always visible. Cultural momentum exists but lacks strong top‑down reinforcement. | I3: Executive leadership visibly prioritizes and reinforces risk culture. This drives strong alignment and reinforces consistent behavior across functions. | J3: Yes
A4: Q003 | B4: All the seniors encourage employees to identify, escalate and report all the concerns in a timely manner | C4: Role Modelling | D4: Leadership Encouragement to Escalate Risks | E4: Indicates whether leaders actively encourage employees to raise concerns and escalate risks early. | F4: Low scores result in hidden risks, delayed escalation, and higher likelihood of issues growing into serious incidents. | G4: Employees do not feel encouraged to raise concerns, resulting in risks remaining hidden until they escalate into major issues. | H4: Employees escalate certain issues but may hesitate in sensitive situations. Early warning signals may still be missed. | I4: Leaders actively encourage escalation, enabling early detection and timely resolution of risks. | J4: No
A5: Q004 | B5: When decisions are made by leaders, potential and long-term implications are usually considered. | C5: Role Modelling | D5: Long-Term Decision Awareness | E5: Measures the extent to which decisions consider long‑term consequences beyond immediate pressures. | F5: Low awareness leads to short‑term decision‑making, recurring problems, and misalignment with long‑term strategy. | G5: Decisions are driven primarily by short‑term pressure, increasing the likelihood of repeated problems and strategic misalignment. | H5: Long‑term implications are considered in some decisions, but consistency is lacking under operational pressure. | I5: Decisions consistently account for long‑term impact, supporting sustainable performance and risk management. | J5: Yes
A6: Q005 | B6: Differences of opinion are respected during discussions about judgments or decisions | C6: Discussability | D6: Openness to Discussions | E6: Reflects how freely employees can discuss concerns, mistakes, and dilemmas. | F6: Low openness suppresses learning, limits problem‑solving, and allows unresolved issues to accumulate. | G6: Employees are reluctant to discuss concerns or mistakes, limiting learning and increasing unresolved risks. | H6: Open discussions occur in some teams but are not consistent across the organization. | I6: Employees freely discuss issues and dilemmas, enabling continuous learning and early risk identification. | J6: Yes
A7: Q006 | B7: I can openly raise concerns without fear of negative consequences | C7: Discussability | D7: Access to Guidance | E7: Shows how easily employees can obtain advice or guidance when facing risk‑related situations | F7: Poor access increases uncertainty, inconsistent decisions, and operational inefficiencies. | G7: Employees struggle to obtain guidance, leading to uncertainty and inconsistent handling of risks. | H7: Guidance is available but not always timely or clear enough for effective decision‑making. | I7: Employees have easy access to guidance, supporting confident and consistent risk decisions. | J7: No
A8: Q007 | B8: Colleagues respond constructively when mistakes or concerns are raised management. | C8: Discussability | D8: Openness to Sharing Opinions | E8: Measures whether employees feel comfortable sharing views and perspectives on risk matters. | F8: Low openness reduces diversity of input, weakens decision quality, and limits early identification of risks. | G8: Employees hesitate to share opinions, limiting diverse perspectives and increasing the chance of blind spots. | H8: Opinions are shared selectively, and some perspectives may remain unheard. | I8: Employees openly share views, strengthening decision quality and risk awareness. | J8: Yes
A9: Q008 | B9: I feel comfortable escalating issues to Risk Management / Ethics & Independence / DPP when needed | C9: Discussability | D9: Comfort in Reporting Risk Dilemmas | E9: Indicates whether employees feel safe raising ethical dilemmas or complex risk situations. | F9: Low comfort discourages reporting, delays resolution, and increases exposure to unmanaged risks. | G9: Employees feel unsafe reporting dilemmas, allowing ethical and risk issues to remain unaddressed. | H9: Some dilemmas are reported, but hesitation remains around sensitive issues. | I9: Employees feel safe raising dilemmas, enabling timely guidance and resolution. | J9: No
A10: Q009 | B10: I have received enough training to handle job‑related challenges effectively. | C10: Achievability | D10: Adequacy of Risk Management Training | E10: Assesses whether employees feel sufficiently trained to manage risk appropriately. | F10: Insufficient training leads to inconsistent behavior, higher error rates, and dependence on individual experience. | G10: Training gaps leave employees ill‑equipped to manage risk, increasing errors and inconsistencies. | H10: Training exists but may not fully address practical risk scenarios. | I10: Training effectively equips employees to manage risks confidently. | J10: Yes
A11: Q010 | B11: Within my team or department people have enough time and resources to do their job without taking unacceptable risks | C11: Achievability | D11: Workload Balance & Resource Sufficiency | E11: Evaluates whether employees have enough time and resources to manage risk effectively. | F11: High workload pressure causes shortcuts, control gaps, and increased operational risk. | G11: High workload prevents employees from properly managing risks, leading to shortcuts and control gaps. | H11: Work pressure occasionally impacts risk quality but remains manageable. | I11: Workload and resources allow employees to consistently manage risks effectively. | J11: Yes
A12: Q011 | B12: People set targets that are achievable without compromising risk management policies, guidelines and procedures. | C12: Achievability | D12: Realistic Target Setting | E12: Measures whether targets and expectations are achievable without compromising risk standards. | F12: Unrealistic targets encourage risk‑taking, policy breaches, and erosion of ethical behavior. | G12: Unrealistic targets encourage risk‑taking and rule‑bypassing behavior. | H12: Targets are generally realistic, but pressure remains in certain situations. | I12: Targets support responsible behavior without compromising risk standards. | J12: Yes
... A33: Q032 | B33: Team members are held to the same behavioral standards, no matter who they are. | C33: Call someone to account | D33: Consistency of Conduct Enforcement | E33: Measures fairness and consistency in applying behavioral rules. | F33: Inconsistent enforcement erodes trust and weakens adherence to standards. | G33: Rules are applied inconsistently, eroding trust and fairness. | H33: Enforcement is generally fair but occasionally inconsistent. | I33: Consistent enforcement reinforces ethical and expected behavior. | J33: Yes

Sheet Sheet2
A3: Dimension x Functions | B3: Functions
A4: Dimension | B4: Audit | C4: Finance | D4: HR | E4: IT | F4: Operations | G4: Sales | H4: Grand Total
A5: Access to Guidance | B5: 95 | C5: 85 | D5: 70 | E5: 76 | F5: 68 | G5: 75 | H5: 77.692308
A6: Accountability for Risk Actions | B6: 90 | C6: 80 | D6: 65 | E6: 76 | F6: 68 | G6: 60 | H6: 73.076923
A7: Adequacy of Risk Management Training | B7: 80 | C7: 75 | D7: 75 | E7: 72 | F7: 60 | G7: 90 | H7: 74.615385
A8: Clarity of Personal Risk Boundaries | B8: 70 | C8: 90 | D8: 80 | E8: 96 | F8: 64 | G8: 80 | H8: 80
A9: Clarity of Role and Responsibilities | B9: 65 | C9: 70 | D9: 75 | E9: 76 | F9: 64 | G9: 60 | H9: 68.461538
A10: Comfort for Reporting Non‑Compliance. | B10: 70 | C10: 70 | D10: 80 | E10: 92 | F10: 64 | G10: 80 | H10: 76.153846
A11: Comfort in Reporting Risk Dilemmas | B11: 90 | C11: 75 | D11: 85 | E11: 88 | F11: 60 | G11: 85 | H11: 80
A12: Compliance Confidence in team | B12: 70 | C12: 85 | D12: 85 | E12: 56 | F12: 64 | G12: 80 | H12: 72.307692
A13: Compliance Recognition & enforcement | B13: 80 | C13: 85 | D13: 75 | E13: 84 | F13: 64 | G13: 80 | H13: 77.692308
A14: Consideration of Impact on Others | B14: 85 | C14: 80 | D14: 70 | E14: 72 | F14: 68 | G14: 80 | H14: 75.384615
A15: Consistency of Conduct Enforcement | B15: 75 | C15: 60 | D15: 85 | E15: 76 | F15: 60 | G15: 75 | H15: 71.538462
A16: Effectiveness of Risk Communication & Training | B16: 75 | C16: 70 | D16: 85 | E16: 76 | F16: 64 | G16: 80 | H16: 74.615385
... A37: Grand Total | B37: 77.03125 | C37: 75.78125 | D37: 76.5625 | E37: 75.375 | F37: 65.875 | G37: 77.5 | H37: 74.375

Sheet Responses
A1: RespondentID | B1: QuestionID | C1: Response | D1: SoftControl | E1: Scores | F1: Score_100 | G1: FavorableFlag | H1: Dimensions | I1: Function
A2: R001 | B2: Q001 | C2: Strongly Agree | D2: =VLOOKUP(Table7[[#This Row],[QuestionID]], FinalQuestions!$A:$C, 3, FALSE) -> Role Modelling | E2: =IF(Table7[[#This Row],[Response]]="","",CHOOSE(MATCH(Table7[[#This Row],[Response]],{"Strongly Agree","Agree","Neutral","Disagree","Strongly Disagree","Not Applicable"},0),5,4,3,2,1,"")) -> 5 | F2: =Table7[[#This Row],[Scores]] * 20 -> 100 | G2: =IF(OR(Table7[[#This Row],[Response]]="Strongly Agree",Table7[[#This Row],[Response]]="Agree"),1,0) -> 1 | H2: =_xlfn.XLOOKUP(Table7[[#This Row],[QuestionID]], FinalQuestions!$A:$A, FinalQuestions!$D:$D,"") -> Leadership Example‑Setting in Risk Management | I2: HR
A3: R001 | B3: Q002 | C3: Disagree | D3: =VLOOKUP(Table7[[#This Row],[QuestionID]], FinalQuestions!$A:$C, 3, FALSE) -> Role Modelling | E3: =IF(Table7[[#This Row],[Response]]="","",CHOOSE(MATCH(Table7[[#This Row],[Response]],{"Strongly Agree","Agree","Neutral","Disagree","Strongly Disagree","Not Applicable"},0),5,4,3,2,1,"")) -> 2 | F3: =Table7[[#This Row],[Scores]] * 20 -> 40 | G3: =IF(OR(Table7[[#This Row],[Response]]="Strongly Agree",Table7[[#This Row],[Response]]="Agree"),1,0) -> 0 | H3: =_xlfn.XLOOKUP(Table7[[#This Row],[QuestionID]], FinalQuestions!$A:$A, FinalQuestions!$D:$D,"") -> Executive Commitment to Risk Culture | I3: HR
A4: R001 | B4: Q003 | C4: Strongly Agree | D4: =VLOOKUP(Table7[[#This Row],[QuestionID]], FinalQuestions!$A:$C, 3, FALSE) -> Role Modelling | E4: =IF(Table7[[#This Row],[Response]]="","",CHOOSE(MATCH(Table7[[#This Row],[Response]],{"Strongly Agree","Agree","Neutral","Disagree","Strongly Disagree","Not Applicable"},0),5,4,3,2,1,"")) -> 5 | F4: =Table7[[#This Row],[Scores]] * 20 -> 100 | G4: =IF(OR(Table7[[#This Row],[Response]]="Strongly Agree",Table7[[#This Row],[Response]]="Agree"),1,0) -> 1 | H4: =_xlfn.XLOOKUP(Table7[[#This Row],[QuestionID]], FinalQuestions!$A:$A, FinalQuestions!$D:$D,"") -> Leadership Encouragement to Escalate Risks | I4: HR
A5: R001 | B5: Q004 | C5: Strongly Agree | D5: =VLOOKUP(Table7[[#This Row],[QuestionID]], FinalQuestions!$A:$C, 3, FALSE) -> Role Modelling | E5: =IF(Table7[[#This Row],[Response]]="","",CHOOSE(MATCH(Table7[[#This Row],[Response]],{"Strongly Agree","Agree","Neutral","Disagree","Strongly Disagree","Not Applicable"},0),5,4,3,2,1,"")) -> 5 | F5: =Table7[[#This Row],[Scores]] * 20 -> 100 | G5: =IF(OR(Table7[[#This Row],[Response]]="Strongly Agree",Table7[[#This Row],[Response]]="Agree"),1,0) -> 1 | H5: =_xlfn.XLOOKUP(Table7[[#This Row],[QuestionID]], FinalQuestions!$A:$A, FinalQuestions!$D:$D,"") -> Long-Term Decision Awareness | I5: HR
A6: R001 | B6: Q005 | C6: Strongly Agree | D6: =VLOOKUP(Table7[[#This Row],[QuestionID]], FinalQuestions!$A:$C, 3, FALSE) -> Discussability | E6: =IF(Table7[[#This Row],[Response]]="","",CHOOSE(MATCH(Table7[[#This Row],[Response]],{"Strongly Agree","Agree","Neutral","Disagree","Strongly Disagree","Not Applicable"},0),5,4,3,2,1,"")) -> 5 | F6: =Table7[[#This Row],[Scores]] * 20 -> 100 | G6: =IF(OR(Table7[[#This Row],[Response]]="Strongly Agree",Table7[[#This Row],[Response]]="Agree"),1,0) -> 1 | H6: =_xlfn.XLOOKUP(Table7[[#This Row],[QuestionID]], FinalQuestions!$A:$A, FinalQuestions!$D:$D,"") -> Openness to Discussions | I6: HR
A7: R001 | B7: Q006 | C7: Strongly Agree | D7: =VLOOKUP(Table7[[#This Row],[QuestionID]], FinalQuestions!$A:$C, 3, FALSE) -> Discussability | E7: =IF(Table7[[#This Row],[Response]]="","",CHOOSE(MATCH(Table7[[#This Row],[Response]],{"Strongly Agree","Agree","Neutral","Disagree","Strongly Disagree","Not Applicable"},0),5,4,3,2,1,"")) -> 5 | F7: =Table7[[#This Row],[Scores]] * 20 -> 100 | G7: =IF(OR(Table7[[#This Row],[Response]]="Strongly Agree",Table7[[#This Row],[Response]]="Agree"),1,0) -> 1 | H7: =_xlfn.XLOOKUP(Table7[[#This Row],[QuestionID]], FinalQuestions!$A:$A, FinalQuestions!$D:$D,"") -> Access to Guidance | I7: HR
A8: R001 | B8: Q007 | C8: Strongly Agree | D8: =VLOOKUP(Table7[[#This Row],[QuestionID]], FinalQuestions!$A:$C, 3, FALSE) -> Discussability | E8: =IF(Table7[[#This Row],[Response]]="","",CHOOSE(MATCH(Table7[[#This Row],[Response]],{"Strongly Agree","Agree","Neutral","Disagree","Strongly Disagree","Not Applicable"},0),5,4,3,2,1,"")) -> 5 | F8: =Table7[[#This Row],[Scores]] * 20 -> 100 | G8: =IF(OR(Table7[[#This Row],[Response]]="Strongly Agree",Table7[[#This Row],[Response]]="Agree"),1,0) -> 1 | H8: =_xlfn.XLOOKUP(Table7[[#This Row],[QuestionID]], FinalQuestions!$A:$A, FinalQuestions!$D:$D,"") -> Openness to Sharing Opinions | I8: HR
A9: R001 | B9: Q008 | C9: Strongly Agree | D9: =VLOOKUP(Table7[[#This Row],[QuestionID]], FinalQuestions!$A:$C, 3, FALSE) -> Discussability | E9: =IF(Table7[[#This Row],[Response]]="","",CHOOSE(MATCH(Table7[[#This Row],[Response]],{"Strongly Agree","Agree","Neutral","Disagree","Strongly Disagree","Not Applicable"},0),5,4,3,2,1,"")) -> 5 | F9: =Table7[[#This Row],[Scores]] * 20 -> 100 | G9: =IF(OR(Table7[[#This Row],[Response]]="Strongly Agree",Table7[[#This Row],[Response]]="Agree"),1,0) -> 1 | H9: =_xlfn.XLOOKUP(Table7[[#This Row],[QuestionID]], FinalQuestions!$A:$A, FinalQuestions!$D:$D,"") -> Comfort in Reporting Risk Dilemmas | I9: HR
A10: R001 | B10: Q009 | C10: Strongly Agree | D10: =VLOOKUP(Table7[[#This Row],[QuestionID]], FinalQuestions!$A:$C, 3, FALSE) -> Achievability | E10: =IF(Table7[[#This Row],[Response]]="","",CHOOSE(MATCH(Table7[[#This Row],[Response]],{"Strongly Agree","Agree","Neutral","Disagree","Strongly Disagree","Not Applicable"},0),5,4,3,2,1,"")) -> 5 | F10: =Table7[[#This Row],[Scores]] * 20 -> 100 | G10: =IF(OR(Table7[[#This Row],[Response]]="Strongly Agree",Table7[[#This Row],[Response]]="Agree"),1,0) -> 1 | H10: =_xlfn.XLOOKUP(Table7[[#This Row],[QuestionID]], FinalQuestions!$A:$A, FinalQuestions!$D:$D,"") -> Adequacy of Risk Management Training | I10: HR
A11: R001 | B11: Q010 | C11: Strongly Agree | D11: =VLOOKUP(Table7[[#This Row],[QuestionID]], FinalQuestions!$A:$C, 3, FALSE) -> Achievability | E11: =IF(Table7[[#This Row],[Response]]="","",CHOOSE(MATCH(Table7[[#This Row],[Response]],{"Strongly Agree","Agree","Neutral","Disagree","Strongly Disagree","Not Applicable"},0),5,4,3,2,1,"")) -> 5 | F11: =Table7[[#This Row],[Scores]] * 20 -> 100 | G11: =IF(OR(Table7[[#This Row],[Response]]="Strongly Agree",Table7[[#This Row],[Response]]="Agree"),1,0) -> 1 | H11: =_xlfn.XLOOKUP(Table7[[#This Row],[QuestionID]], FinalQuestions!$A:$A, FinalQuestions!$D:$D,"") -> Workload Balance & Resource Sufficiency | I11: HR
A12: R001 | B12: Q011 | C12: Strongly Agree | D12: =VLOOKUP(Table7[[#This Row],[QuestionID]], FinalQuestions!$A:$C, 3, FALSE) -> Achievability | E12: =IF(Table7[[#This Row],[Response]]="","",CHOOSE(MATCH(Table7[[#This Row],[Response]],{"Strongly Agree","Agree","Neutral","Disagree","Strongly Disagree","Not Applicable"},0),5,4,3,2,1,"")) -> 5 | F12: =Table7[[#This Row],[Scores]] * 20 -> 100 | G12: =IF(OR(Table7[[#This Row],[Response]]="Strongly Agree",Table7[[#This Row],[Response]]="Agree"),1,0) -> 1 | H12: =_xlfn.XLOOKUP(Table7[[#This Row],[QuestionID]], FinalQuestions!$A:$A, FinalQuestions!$D:$D,"") -> Realistic Target Setting | I12: HR
A13: R001 | B13: Q012 | C13: Strongly Agree | D13: =VLOOKUP(Table7[[#This Row],[QuestionID]], FinalQuestions!$A:$C, 3, FALSE) -> Achievability | E13: =IF(Table7[[#This Row],[Response]]="","",CHOOSE(MATCH(Table7[[#This Row],[Response]],{"Strongly Agree","Agree","Neutral","Disagree","Strongly Disagree","Not Applicable"},0),5,4,3,2,1,"")) -> 5 | F13: =Table7[[#This Row],[Scores]] * 20 -> 100 | G13: =IF(OR(Table7[[#This Row],[Response]]="Strongly Agree",Table7[[#This Row],[Response]]="Agree"),1,0) -> 1 | H13: =_xlfn.XLOOKUP(Table7[[#This Row],[QuestionID]], FinalQuestions!$A:$A, FinalQuestions!$D:$D,"") -> Risk Insight in Decision Making | I13: HR
... A833: R025 | B833: Q032 | C833: Agree | D833: =VLOOKUP(Table7[[#This Row],[QuestionID]], FinalQuestions!$A:$C, 3, FALSE) -> Call someone to account | E833: =IF(Table7[[#This Row],[Response]]="","",CHOOSE(MATCH(Table7[[#This Row],[Response]],{"Strongly Agree","Agree","Neutral","Disagree","Strongly Disagree","Not Applicable"},0),5,4,3,2,1,"")) -> 4 | F833: =Table7[[#This Row],[Scores]] * 20 -> 80 | G833: =IF(OR(Table7[[#This Row],[Response]]="Strongly Agree",Table7[[#This Row],[Response]]="Agree"),1,0) -> 1 | H833: =_xlfn.XLOOKUP(Table7[[#This Row],[QuestionID]], FinalQuestions!$A:$A, FinalQuestions!$D:$D,"") -> Consistency of Conduct Enforcement | I833: Finance

Sheet Function_SC
A1: Funtions x SoftControls | B1: {=TRANSPOSE(_xlfn._xlws.SORT(_xlfn.UNIQUE(_xlfn._xlws.FILTER(Responses!$D:$D,(Responses!$D:$D<>"")*(Responses!$D:$D<>"SoftControl")))))} -> Achievability | C1: Call someone to account | D1: Clarity | E1: Commitment | F1: Discussability | G1: Enforcement | H1: Role Modelling | I1: Transparency
A2: {=_xlfn._xlws.SORT(_xlfn.UNIQUE(_xlfn._xlws.FILTER(Responses!$I:$I,(Responses!$I:$I<>"")*(Responses!$I:$I<>"Function"))))} -> Audit | B2: =_xlfn.LET(_xlpm.func,$A2,_xlpm.sc,B$1,AVERAGEIFS(Responses!$F:$F,Responses!$I:$I,_xlpm.func,Responses!$D:$D,_xlpm.sc)) -> 72.5 | C2: =_xlfn.LET(_xlpm.func,$A2,_xlpm.sc,C$1,AVERAGEIFS(Responses!$F:$F,Responses!$I:$I,_xlpm.func,Responses!$D:$D,_xlpm.sc)) -> 71.25 | D2: =_xlfn.LET(_xlpm.func,$A2,_xlpm.sc,D$1,AVERAGEIFS(Responses!$F:$F,Responses!$I:$I,_xlpm.func,Responses!$D:$D,_xlpm.sc)) -> 66.25 | E2: =_xlfn.LET(_xlpm.func,$A2,_xlpm.sc,E$1,AVERAGEIFS(Responses!$F:$F,Responses!$I:$I,_xlpm.func,Responses!$D:$D,_xlpm.sc)) -> 81.25 | F2: =_xlfn.LET(_xlpm.func,$A2,_xlpm.sc,F$1,AVERAGEIFS(Responses!$F:$F,Responses!$I:$I,_xlpm.func,Responses!$D:$D,_xlpm.sc)) -> 92.5 | G2: =_xlfn.LET(_xlpm.func,$A2,_xlpm.sc,G$1,AVERAGEIFS(Responses!$F:$F,Responses!$I:$I,_xlpm.func,Responses!$D:$D,_xlpm.sc)) -> 75 | H2: =_xlfn.LET(_xlpm.func,$A2,_xlpm.sc,H$1,AVERAGEIFS(Responses!$F:$F,Responses!$I:$I,_xlpm.func,Responses!$D:$D,_xlpm.sc)) -> 81.25 | I2: =_xlfn.LET(_xlpm.func,$A2,_xlpm.sc,I$1,AVERAGEIFS(Responses!$F:$F,Responses!$I:$I,_xlpm.func,Responses!$D:$D,_xlpm.sc)) -> 76.25
A3: Finance | B3: =_xlfn.LET(_xlpm.func,$A3,_xlpm.sc,B$1,AVERAGEIFS(Responses!$F:$F,Responses!$I:$I,_xlpm.func,Responses!$D:$D,_xlpm.sc)) -> 73.75 | C3: =_xlfn.LET(_xlpm.func,$A3,_xlpm.sc,C$1,AVERAGEIFS(Responses!$F:$F,Responses!$I:$I,_xlpm.func,Responses!$D:$D,_xlpm.sc)) -> 55 | D3: =_xlfn.LET(_xlpm.func,$A3,_xlpm.sc,D$1,AVERAGEIFS(Responses!$F:$F,Responses!$I:$I,_xlpm.func,Responses!$D:$D,_xlpm.sc)) -> 81.25 | E3: =_xlfn.LET(_xlpm.func,$A3,_xlpm.sc,E$1,AVERAGEIFS(Responses!$F:$F,Responses!$I:$I,_xlpm.func,Responses!$D:$D,_xlpm.sc)) -> 73.75 | F3: =_xlfn.LET(_xlpm.func,$A3,_xlpm.sc,F$1,AVERAGEIFS(Responses!$F:$F,Responses!$I:$I,_xlpm.func,Responses!$D:$D,_xlpm.sc)) -> 80 | G3: =_xlfn.LET(_xlpm.func,$A3,_xlpm.sc,G$1,AVERAGEIFS(Responses!$F:$F,Responses!$I:$I,_xlpm.func,Responses!$D:$D,_xlpm.sc)) -> 80 | H3: =_xlfn.LET(_xlpm.func,$A3,_xlpm.sc,H$1,AVERAGEIFS(Responses!$F:$F,Responses!$I:$I,_xlpm.func,Responses!$D:$D,_xlpm.sc)) -> 80 | I3: =_xlfn.LET(_xlpm.func,$A3,_xlpm.sc,I$1,AVERAGEIFS(Responses!$F:$F,Responses!$I:$I,_xlpm.func,Responses!$D:$D,_xlpm.sc)) -> 82.5
A4: HR | B4: =_xlfn.LET(_xlpm.func,$A4,_xlpm.sc,B$1,AVERAGEIFS(Responses!$F:$F,Responses!$I:$I,_xlpm.func,Responses!$D:$D,_xlpm.sc)) -> 76.25 | C4: =_xlfn.LET(_xlpm.func,$A4,_xlpm.sc,C$1,AVERAGEIFS(Responses!$F:$F,Responses!$I:$I,_xlpm.func,Responses!$D:$D,_xlpm.sc)) -> 76.25 | D4: =_xlfn.LET(_xlpm.func,$A4,_xlpm.sc,D$1,AVERAGEIFS(Responses!$F:$F,Responses!$I:$I,_xlpm.func,Responses!$D:$D,_xlpm.sc)) -> 80 | E4: =_xlfn.LET(_xlpm.func,$A4,_xlpm.sc,E$1,AVERAGEIFS(Responses!$F:$F,Responses!$I:$I,_xlpm.func,Responses!$D:$D,_xlpm.sc)) -> 75 | F4: =_xlfn.LET(_xlpm.func,$A4,_xlpm.sc,F$1,AVERAGEIFS(Responses!$F:$F,Responses!$I:$I,_xlpm.func,Responses!$D:$D,_xlpm.sc)) -> 76.25 | G4: =_xlfn.LET(_xlpm.func,$A4,_xlpm.sc,G$1,AVERAGEIFS(Responses!$F:$F,Responses!$I:$I,_xlpm.func,Responses!$D:$D,_xlpm.sc)) -> 76.25 | H4: =_xlfn.LET(_xlpm.func,$A4,_xlpm.sc,H$1,AVERAGEIFS(Responses!$F:$F,Responses!$I:$I,_xlpm.func,Responses!$D:$D,_xlpm.sc)) -> 75 | I4: =_xlfn.LET(_xlpm.func,$A4,_xlpm.sc,I$1,AVERAGEIFS(Responses!$F:$F,Responses!$I:$I,_xlpm.func,Responses!$D:$D,_xlpm.sc)) -> 77.5
A5: IT | B5: =_xlfn.LET(_xlpm.func,$A5,_xlpm.sc,B$1,AVERAGEIFS(Responses!$F:$F,Responses!$I:$I,_xlpm.func,Responses!$D:$D,_xlpm.sc)) -> 71 | C5: =_xlfn.LET(_xlpm.func,$A5,_xlpm.sc,C$1,AVERAGEIFS(Responses!$F:$F,Responses!$I:$I,_xlpm.func,Responses!$D:$D,_xlpm.sc)) -> 80 | D5: =_xlfn.LET(_xlpm.func,$A5,_xlpm.sc,D$1,AVERAGEIFS(Responses!$F:$F,Responses!$I:$I,_xlpm.func,Responses!$D:$D,_xlpm.sc)) -> 83 | E5: =_xlfn.LET(_xlpm.func,$A5,_xlpm.sc,E$1,AVERAGEIFS(Responses!$F:$F,Responses!$I:$I,_xlpm.func,Responses!$D:$D,_xlpm.sc)) -> 72 | F5: =_xlfn.LET(_xlpm.func,$A5,_xlpm.sc,F$1,AVERAGEIFS(Responses!$F:$F,Responses!$I:$I,_xlpm.func,Responses!$D:$D,_xlpm.sc)) -> 78 | G5: =_xlfn.LET(_xlpm.func,$A5,_xlpm.sc,G$1,AVERAGEIFS(Responses!$F:$F,Responses!$I:$I,_xlpm.func,Responses!$D:$D,_xlpm.sc)) -> 75 | H5: =_xlfn.LET(_xlpm.func,$A5,_xlpm.sc,H$1,AVERAGEIFS(Responses!$F:$F,Responses!$I:$I,_xlpm.func,Responses!$D:$D,_xlpm.sc)) -> 74 | I5: =_xlfn.LET(_xlpm.func,$A5,_xlpm.sc,I$1,AVERAGEIFS(Responses!$F:$F,Responses!$I:$I,_xlpm.func,Responses!$D:$D,_xlpm.sc)) -> 70
A6: Operations | B6: =_xlfn.LET(_xlpm.func,$A6,_xlpm.sc,B$1,AVERAGEIFS(Responses!$F:$F,Responses!$I:$I,_xlpm.func,Responses!$D:$D,_xlpm.sc)) -> 60 | C6: =_xlfn.LET(_xlpm.func,$A6,_xlpm.sc,C$1,AVERAGEIFS(Responses!$F:$F,Responses!$I:$I,_xlpm.func,Responses!$D:$D,_xlpm.sc)) -> 64 | D6: =_xlfn.LET(_xlpm.func,$A6,_xlpm.sc,D$1,AVERAGEIFS(Responses!$F:$F,Responses!$I:$I,_xlpm.func,Responses!$D:$D,_xlpm.sc)) -> 64 | E6: =_xlfn.LET(_xlpm.func,$A6,_xlpm.sc,E$1,AVERAGEIFS(Responses!$F:$F,Responses!$I:$I,_xlpm.func,Responses!$D:$D,_xlpm.sc)) -> 70 | F6: =_xlfn.LET(_xlpm.func,$A6,_xlpm.sc,F$1,AVERAGEIFS(Responses!$F:$F,Responses!$I:$I,_xlpm.func,Responses!$D:$D,_xlpm.sc)) -> 66 | G6: =_xlfn.LET(_xlpm.func,$A6,_xlpm.sc,G$1,AVERAGEIFS(Responses!$F:$F,Responses!$I:$I,_xlpm.func,Responses!$D:$D,_xlpm.sc)) -> 67 | H6: =_xlfn.LET(_xlpm.func,$A6,_xlpm.sc,H$1,AVERAGEIFS(Responses!$F:$F,Responses!$I:$I,_xlpm.func,Responses!$D:$D,_xlpm.sc)) -> 67 | I6: =_xlfn.LET(_xlpm.func,$A6,_xlpm.sc,I$1,AVERAGEIFS(Responses!$F:$F,Responses!$I:$I,_xlpm.func,Responses!$D:$D,_xlpm.sc)) -> 69
A7: Sales | B7: =_xlfn.LET(_xlpm.func,$A7,_xlpm.sc,B$1,AVERAGEIFS(Responses!$F:$F,Responses!$I:$I,_xlpm.func,Responses!$D:$D,_xlpm.sc)) -> 82.5 | C7: =_xlfn.LET(_xlpm.func,$A7,_xlpm.sc,C$1,AVERAGEIFS(Responses!$F:$F,Responses!$I:$I,_xlpm.func,Responses!$D:$D,_xlpm.sc)) -> 73.75 | D7: =_xlfn.LET(_xlpm.func,$A7,_xlpm.sc,D$1,AVERAGEIFS(Responses!$F:$F,Responses!$I:$I,_xlpm.func,Responses!$D:$D,_xlpm.sc)) -> 75 | E7: =_xlfn.LET(_xlpm.func,$A7,_xlpm.sc,E$1,AVERAGEIFS(Responses!$F:$F,Responses!$I:$I,_xlpm.func,Responses!$D:$D,_xlpm.sc)) -> 76.25 | F7: =_xlfn.LET(_xlpm.func,$A7,_xlpm.sc,F$1,AVERAGEIFS(Responses!$F:$F,Responses!$I:$I,_xlpm.func,Responses!$D:$D,_xlpm.sc)) -> 77.5 | G7: =_xlfn.LET(_xlpm.func,$A7,_xlpm.sc,G$1,AVERAGEIFS(Responses!$F:$F,Responses!$I:$I,_xlpm.func,Responses!$D:$D,_xlpm.sc)) -> 78.75 | H7: =_xlfn.LET(_xlpm.func,$A7,_xlpm.sc,H$1,AVERAGEIFS(Responses!$F:$F,Responses!$I:$I,_xlpm.func,Responses!$D:$D,_xlpm.sc)) -> 77.5 | I7: =_xlfn.LET(_xlpm.func,$A7,_xlpm.sc,I$1,AVERAGEIFS(Responses!$F:$F,Responses!$I:$I,_xlpm.func,Responses!$D:$D,_xlpm.sc)) -> 78.75
A10: Funtion | B10: RCI
A11: {=_xlfn._xlws.SORT(_xlfn.UNIQUE(_xlfn._xlws.FILTER(Responses!$I:$I,(Responses!$I:$I<>"")*(Responses!$I:$I<>"Function"))))} -> Audit | B11: =IFERROR(ROUND(AVERAGEIFS(Responses!$F:$F,Responses!$I:$I,$A2),0),"") -> 77
A12: Finance | B12: =IFERROR(ROUND(AVERAGEIFS(Responses!$F:$F,Responses!$I:$I,$A3),0),"") -> 76
A13: HR | B13: =IFERROR(ROUND(AVERAGEIFS(Responses!$F:$F,Responses!$I:$I,$A4),0),"") -> 77
A14: IT | B14: =IFERROR(ROUND(AVERAGEIFS(Responses!$F:$F,Responses!$I:$I,$A5),0),"") -> 75
A15: Operations | B15: =IFERROR(ROUND(AVERAGEIFS(Responses!$F:$F,Responses!$I:$I,$A6),0),"") -> 66
A16: Sales | B16: =IFERROR(ROUND(AVERAGEIFS(Responses!$F:$F,Responses!$I:$I,$A7),0),"") -> 78
A26: KPI | B26: Value
A27: Best Funtion | B27: =INDEX($A$10:$A$16,MATCH(MAX($B$10:$B$16),$B$10:$B$16,0))& "(" & MAX($B$10:$B$16)& ")" -> Sales(78)
A28: Worst Funtion | B28: =INDEX($A$10:$A$16, MATCH(MIN($B$10:$B$16), $B$10:$B$16, 0)) & " (" & MIN($B$10:$B$16) & ")" -> Operations (66)

Sheet Sheet1

Sheet Culture_Risk_Index
A1: Metric | B1: Value
A2: Risk Culture Index | B2: =IFERROR(AVERAGE(Responses!$F:$F), "") -> 74.375
A3: Total Respondents | B3: =COUNTA(_xlfn.UNIQUE(Responses!$A:$A)) -> 27
A4: Total Questions | B4: =COUNTA(FinalQuestions!$A:$A) - 1 -> 32
A5: Overall Favorable % | B5: =SUM(Responses!$G:$G) / COUNTA(Responses!$G:$G)*100 -> 56.182473
A6: Overall Risk Level | B6: =IF(B2>=80,"Low",IF(B2>=60,"Medium","High")) -> Medium
L9: ="RCI Score: "&TEXT(B2,"0")&"%" -> RCI Score: 74% | P9: Risk Culture Index
P10: =IFERROR(AVERAGE(Responses!$F:$F), "") -> 74.375
A34: High Risk | B34: 1.8
A35: Med Risk | B35: 0.6
A36: Low Risk | B36: 0.6
A37: Hidden | B37: 1
A38: hidden | B38: 1
A39: hidden | B39: 1
A55: Column1 | B55: Column2
A56: StartPadding | B56: =B2*1.8 -> 133.875
A57: Needle | B57: 1
A58: End Padding | B58: =360 - B56 - B57 -> 225.125
A72: SoftControl | B72: Score
A73: Role Modelling | B73: =IFERROR(ROUND(AVERAGEIFS(Responses!$F:$F,Responses!$D:$D,$A73),0),"") -> 75
A74: Discussability | B74: =IFERROR(ROUND(AVERAGEIFS(Responses!$F:$F,Responses!$D:$D,$A74),0),"") -> 78
A75: Achievability | B75: =IFERROR(ROUND(AVERAGEIFS(Responses!$F:$F,Responses!$D:$D,$A75),0),"") -> 72
A76: Enforcement | B76: =IFERROR(ROUND(AVERAGEIFS(Responses!$F:$F,Responses!$D:$D,$A76),0),"") -> 75
A77: Clarity | B77: =IFERROR(ROUND(AVERAGEIFS(Responses!$F:$F,Responses!$D:$D,$A77),0),"") -> 75
A78: Transparency | B78: =IFERROR(ROUND(AVERAGEIFS(Responses!$F:$F,Responses!$D:$D,$A78),0),"") -> 75
A79: Commitment | B79: =IFERROR(ROUND(AVERAGEIFS(Responses!$F:$F,Responses!$D:$D,$A79),0),"") -> 74
A80: Call someone to account | B80: =IFERROR(ROUND(AVERAGEIFS(Responses!$F:$F,Responses!$D:$D,$A80),0),"") -> 70

Sheet Sector benchmark score
A1: Sector | B1: Transparency | C1: Clarity | D1: Achievability | E1: Role Modelling | F1: Commitment | G1: Discussability | H1: Calling to Account | I1: Enforcement
A2: Banking & Capital Markets | B2: 78 | C2: 88 | D2: 72 | E2: 80 | F2: 82 | G2: 74 | H2: 76 | I2: 84
A3: Insurance | B3: 76 | C3: 86 | D3: 74 | E3: 79 | F3: 83 | G3: 73 | H3: 75 | I3: 83
A4: Technology, Media & Telecom | B4: 72 | C4: 80 | D4: 70 | E4: 77 | F4: 85 | G4: 82 | H4: 68 | I4: 72
A5: Healthcare & Life Sciences | B5: 70 | C5: 84 | D5: 68 | E5: 78 | F5: 87 | G5: 72 | H5: 70 | I5: 76
A6: Energy & Natural Resources | B6: 68 | C6: 82 | D6: 66 | E6: 76 | F6: 80 | G6: 70 | H6: 72 | I6: 78
A7: Government & Public Sector | B7: 66 | C7: 85 | D7: 60 | E7: 74 | F7: 79 | G7: 69 | H7: 65 | I7: 73
A8: Consumer Goods & Retail | B8: 72 | C8: 82 | D8: 71 | E8: 76 | F8: 81 | G8: 74 | H8: 69 | I8: 71
A9: Industrial Manufacturing | B9: 70 | C9: 84 | D9: 72 | E9: 75 | F9: 80 | G9: 68 | H9: 73 | I9: 77
A10: Infrastructure & Transport | B10: 69 | C10: 83 | D10: 65 | E10: 74 | F10: 78 | G10: 67 | H10: 72 | I10: 76
A11: Real Estate & Construction | B11: 68 | C11: 81 | D11: 64 | E11: 73 | F11: 77 | G11: 66 | H11: 70 | I11: 74

Sheet Summary
A1: RespondentID | B1: SoftControl | C1: Avg Scores | D1: AvgScore100 | E1: Favorable% | F1: Total_Qs
A2: R001 | B2: Role Modelling | C2: =IFERROR(AVERAGEIFS(Responses!$E:$E,Responses!$A:$A,$A2,Responses!$D:$D,$B2),"") -> 4.25 | D2: =IFERROR(AVERAGEIFS(Responses!$F:$F,Responses!$A:$A,$A2,Responses!$D:$D,$B2),"") -> 85 | E2: =IFERROR(SUMIFS(Responses!$G:$G,Responses!$A:$A,$A2,Responses!$D:$D,$B2)/COUNTIFS(Responses!$A:$A,$A2,Responses!$D:$D,$B2),0)*100 -> 75 | F2: =COUNTIFS(Responses!$A:$A,$A2,Responses!$D:$D,$B2) -> 4
A3: R001 | B3: Discussability | C3: =IFERROR(AVERAGEIFS(Responses!$E:$E,Responses!$A:$A,$A3,Responses!$D:$D,$B3),"") -> 5 | D3: =IFERROR(AVERAGEIFS(Responses!$F:$F,Responses!$A:$A,$A3,Responses!$D:$D,$B3),"") -> 100 | E3: =IFERROR(SUMIFS(Responses!$G:$G,Responses!$A:$A,$A3,Responses!$D:$D,$B3)/COUNTIFS(Responses!$A:$A,$A3,Responses!$D:$D,$B3),0)*100 -> 100 | F3: =COUNTIFS(Responses!$A:$A,$A3,Responses!$D:$D,$B3) -> 4
A4: R001 | B4: Achievability | C4: =IFERROR(AVERAGEIFS(Responses!$E:$E,Responses!$A:$A,$A4,Responses!$D:$D,$B4),"") -> 5 | D4: =IFERROR(AVERAGEIFS(Responses!$F:$F,Responses!$A:$A,$A4,Responses!$D:$D,$B4),"") -> 100 | E4: =IFERROR(SUMIFS(Responses!$G:$G,Responses!$A:$A,$A4,Responses!$D:$D,$B4)/COUNTIFS(Responses!$A:$A,$A4,Responses!$D:$D,$B4),0)*100 -> 100 | F4: =COUNTIFS(Responses!$A:$A,$A4,Responses!$D:$D,$B4) -> 4
A5: R001 | B5: Enforcement | C5: =IFERROR(AVERAGEIFS(Responses!$E:$E,Responses!$A:$A,$A5,Responses!$D:$D,$B5),"") -> 5 | D5: =IFERROR(AVERAGEIFS(Responses!$F:$F,Responses!$A:$A,$A5,Responses!$D:$D,$B5),"") -> 100 | E5: =IFERROR(SUMIFS(Responses!$G:$G,Responses!$A:$A,$A5,Responses!$D:$D,$B5)/COUNTIFS(Responses!$A:$A,$A5,Responses!$D:$D,$B5),0)*100 -> 100 | F5: =COUNTIFS(Responses!$A:$A,$A5,Responses!$D:$D,$B5) -> 4
A6: R001 | B6: Clarity | C6: =IFERROR(AVERAGEIFS(Responses!$E:$E,Responses!$A:$A,$A6,Responses!$D:$D,$B6),"") -> 5 | D6: =IFERROR(AVERAGEIFS(Responses!$F:$F,Responses!$A:$A,$A6,Responses!$D:$D,$B6),"") -> 100 | E6: =IFERROR(SUMIFS(Responses!$G:$G,Responses!$A:$A,$A6,Responses!$D:$D,$B6)/COUNTIFS(Responses!$A:$A,$A6,Responses!$D:$D,$B6),0)*100 -> 100 | F6: =COUNTIFS(Responses!$A:$A,$A6,Responses!$D:$D,$B6) -> 4
A7: R001 | B7: Transparency | C7: =IFERROR(AVERAGEIFS(Responses!$E:$E,Responses!$A:$A,$A7,Responses!$D:$D,$B7),"") -> 5 | D7: =IFERROR(AVERAGEIFS(Responses!$F:$F,Responses!$A:$A,$A7,Responses!$D:$D,$B7),"") -> 100 | E7: =IFERROR(SUMIFS(Responses!$G:$G,Responses!$A:$A,$A7,Responses!$D:$D,$B7)/COUNTIFS(Responses!$A:$A,$A7,Responses!$D:$D,$B7),0)*100 -> 100 | F7: =COUNTIFS(Responses!$A:$A,$A7,Responses!$D:$D,$B7) -> 4
A8: R001 | B8: Commitment | C8: =IFERROR(AVERAGEIFS(Responses!$E:$E,Responses!$A:$A,$A8,Responses!$D:$D,$B8),"") -> 5 | D8: =IFERROR(AVERAGEIFS(Responses!$F:$F,Responses!$A:$A,$A8,Responses!$D:$D,$B8),"") -> 100 | E8: =IFERROR(SUMIFS(Responses!$G:$G,Responses!$A:$A,$A8,Responses!$D:$D,$B8)/COUNTIFS(Responses!$A:$A,$A8,Responses!$D:$D,$B8),0)*100 -> 100 | F8: =COUNTIFS(Responses!$A:$A,$A8,Responses!$D:$D,$B8) -> 4
A9: R001 | B9: Call someone to account | C9: =IFERROR(AVERAGEIFS(Responses!$E:$E,Responses!$A:$A,$A9,Responses!$D:$D,$B9),"") -> 5 | D9: =IFERROR(AVERAGEIFS(Responses!$F:$F,Responses!$A:$A,$A9,Responses!$D:$D,$B9),"") -> 100 | E9: =IFERROR(SUMIFS(Responses!$G:$G,Responses!$A:$A,$A9,Responses!$D:$D,$B9)/COUNTIFS(Responses!$A:$A,$A9,Responses!$D:$D,$B9),0)*100 -> 100 | F9: =COUNTIFS(Responses!$A:$A,$A9,Responses!$D:$D,$B9) -> 4
A10: R002 | B10: Role Modelling | C10: =IFERROR(AVERAGEIFS(Responses!$E:$E,Responses!$A:$A,$A10,Responses!$D:$D,$B10),"") -> 5 | D10: =IFERROR(AVERAGEIFS(Responses!$F:$F,Responses!$A:$A,$A10,Responses!$D:$D,$B10),"") -> 100 | E10: =IFERROR(SUMIFS(Responses!$G:$G,Responses!$A:$A,$A10,Responses!$D:$D,$B10)/COUNTIFS(Responses!$A:$A,$A10,Responses!$D:$D,$B10),0)*100 -> 100 | F10: =COUNTIFS(Responses!$A:$A,$A10,Responses!$D:$D,$B10) -> 4
A11: R002 | B11: Discussability | C11: =IFERROR(AVERAGEIFS(Responses!$E:$E,Responses!$A:$A,$A11,Responses!$D:$D,$B11),"") -> 5 | D11: =IFERROR(AVERAGEIFS(Responses!$F:$F,Responses!$A:$A,$A11,Responses!$D:$D,$B11),"") -> 100 | E11: =IFERROR(SUMIFS(Responses!$G:$G,Responses!$A:$A,$A11,Responses!$D:$D,$B11)/COUNTIFS(Responses!$A:$A,$A11,Responses!$D:$D,$B11),0)*100 -> 100 | F11: =COUNTIFS(Responses!$A:$A,$A11,Responses!$D:$D,$B11) -> 4
A12: R002 | B12: Achievability | C12: =IFERROR(AVERAGEIFS(Responses!$E:$E,Responses!$A:$A,$A12,Responses!$D:$D,$B12),"") -> 5 | D12: =IFERROR(AVERAGEIFS(Responses!$F:$F,Responses!$A:$A,$A12,Responses!$D:$D,$B12),"") -> 100 | E12: =IFERROR(SUMIFS(Responses!$G:$G,Responses!$A:$A,$A12,Responses!$D:$D,$B12)/COUNTIFS(Responses!$A:$A,$A12,Responses!$D:$D,$B12),0)*100 -> 100 | F12: =COUNTIFS(Responses!$A:$A,$A12,Responses!$D:$D,$B12) -> 4
A13: R002 | B13: Enforcement | C13: =IFERROR(AVERAGEIFS(Responses!$E:$E,Responses!$A:$A,$A13,Responses!$D:$D,$B13),"") -> 5 | D13: =IFERROR(AVERAGEIFS(Responses!$F:$F,Responses!$A:$A,$A13,Responses!$D:$D,$B13),"") -> 100 | E13: =IFERROR(SUMIFS(Responses!$G:$G,Responses!$A:$A,$A13,Responses!$D:$D,$B13)/COUNTIFS(Responses!$A:$A,$A13,Responses!$D:$D,$B13),0)*100 -> 100 | F13: =COUNTIFS(Responses!$A:$A,$A13,Responses!$D:$D,$B13) -> 4
... A201: R025 | B201: Call someone to account | C201: =IFERROR(AVERAGEIFS(Responses!$E:$E,Responses!$A:$A,$A201,Responses!$D:$D,$B201),"") -> 3.5 | D201: =IFERROR(AVERAGEIFS(Responses!$F:$F,Responses!$A:$A,$A201,Responses!$D:$D,$B201),"") -> 70 | E201: =IFERROR(SUMIFS(Responses!$G:$G,Responses!$A:$A,$A201,Responses!$D:$D,$B201)/COUNTIFS(Responses!$A:$A,$A201,Responses!$D:$D,$B201),0)*100 -> 50 | F201: =COUNTIFS(Responses!$A:$A,$A201,Responses!$D:$D,$B201) -> 4

Sheet SOFT CONTROL SCORECARD
A1: SoftControl | B1: Avg Scores | C1: AvgScore100 | D1: Total_Questions | E1: Favorable% | F1: Risk_Level
A2: Role Modelling | B2: =AVERAGEIF(Responses!$D:$D, A2, Responses!$E:$E) -> 3.7692308 | C2: =IFERROR(ROUND(AVERAGEIF(Responses!$D:$D, A2, Responses!$F:$F), 0), "") -> 75 | D2: =COUNTIF(FinalQuestions!C:C, A2) -> 4 | E2: =SUMIFS(Responses!G:G, Responses!D:D, A2) / COUNTIFS(Responses!D:D, A2)*100 -> 58.653846 | F2: =IF(Table9[[#This Row],[AvgScore100]]>=80,"Low",IF(Table9[[#This Row],[AvgScore100]]>=70,"Medium","High")) -> Medium
A3: Discussability | B3: =AVERAGEIF(Responses!$D:$D, A3, Responses!$E:$E) -> 3.8942308 | C3: =IFERROR(ROUND(AVERAGEIF(Responses!$D:$D, A3, Responses!$F:$F), 0), "") -> 78 | D3: =COUNTIF(FinalQuestions!C:C, A3) -> 4 | E3: =SUMIFS(Responses!G:G, Responses!D:D, A3) / COUNTIFS(Responses!D:D, A3)*100 -> 61.538462 | F3: =IF(Table9[[#This Row],[AvgScore100]]>=80,"Low",IF(Table9[[#This Row],[AvgScore100]]>=70,"Medium","High")) -> Medium
A4: Achievability | B4: =AVERAGEIF(Responses!$D:$D, A4, Responses!$E:$E) -> 3.6057692 | C4: =IFERROR(ROUND(AVERAGEIF(Responses!$D:$D, A4, Responses!$F:$F), 0), "") -> 72 | D4: =COUNTIF(FinalQuestions!C:C, A4) -> 4 | E4: =SUMIFS(Responses!G:G, Responses!D:D, A4) / COUNTIFS(Responses!D:D, A4)*100 -> 53.846154 | F4: =IF(Table9[[#This Row],[AvgScore100]]>=80,"Low",IF(Table9[[#This Row],[AvgScore100]]>=70,"Medium","High")) -> Medium
A5: Enforcement | B5: =AVERAGEIF(Responses!$D:$D, A5, Responses!$E:$E) -> 3.75 | C5: =IFERROR(ROUND(AVERAGEIF(Responses!$D:$D, A5, Responses!$F:$F), 0), "") -> 75 | D5: =COUNTIF(FinalQuestions!C:C, A5) -> 4 | E5: =SUMIFS(Responses!G:G, Responses!D:D, A5) / COUNTIFS(Responses!D:D, A5)*100 -> 55.769231 | F5: =IF(Table9[[#This Row],[AvgScore100]]>=80,"Low",IF(Table9[[#This Row],[AvgScore100]]>=70,"Medium","High")) -> Medium
A6: Clarity | B6: =AVERAGEIF(Responses!$D:$D, A6, Responses!$E:$E) -> 3.7403846 | C6: =IFERROR(ROUND(AVERAGEIF(Responses!$D:$D, A6, Responses!$F:$F), 0), "") -> 75 | D6: =COUNTIF(FinalQuestions!C:C, A6) -> 4 | E6: =SUMIFS(Responses!G:G, Responses!D:D, A6) / COUNTIFS(Responses!D:D, A6)*100 -> 54.807692 | F6: =IF(Table9[[#This Row],[AvgScore100]]>=80,"Low",IF(Table9[[#This Row],[AvgScore100]]>=70,"Medium","High")) -> Medium
A7: Transparency | B7: =AVERAGEIF(Responses!$D:$D, A7, Responses!$E:$E) -> 3.7596154 | C7: =IFERROR(ROUND(AVERAGEIF(Responses!$D:$D, A7, Responses!$F:$F), 0), "") -> 75 | D7: =COUNTIF(FinalQuestions!C:C, A7) -> 4 | E7: =SUMIFS(Responses!G:G, Responses!D:D, A7) / COUNTIFS(Responses!D:D, A7)*100 -> 57.692308 | F7: =IF(Table9[[#This Row],[AvgScore100]]>=80,"Low",IF(Table9[[#This Row],[AvgScore100]]>=70,"Medium","High")) -> Medium
A8: Commitment | B8: =AVERAGEIF(Responses!$D:$D, A8, Responses!$E:$E) -> 3.7211538 | C8: =IFERROR(ROUND(AVERAGEIF(Responses!$D:$D, A8, Responses!$F:$F), 0), "") -> 74 | D8: =COUNTIF(FinalQuestions!C:C, A8) -> 4 | E8: =SUMIFS(Responses!G:G, Responses!D:D, A8) / COUNTIFS(Responses!D:D, A8)*100 -> 58.653846 | F8: =IF(Table9[[#This Row],[AvgScore100]]>=80,"Low",IF(Table9[[#This Row],[AvgScore100]]>=70,"Medium","High")) -> Medium
A9: Call Someone to Account | B9: =AVERAGEIF(Responses!$D:$D, A9, Responses!$E:$E) -> 3.5096154 | C9: =IFERROR(ROUND(AVERAGEIF(Responses!$D:$D, A9, Responses!$F:$F), 0), "") -> 70 | D9: =COUNTIF(FinalQuestions!C:C, A9) -> 4 | E9: =SUMIFS(Responses!G:G, Responses!D:D, A9) / COUNTIFS(Responses!D:D, A9)*100 -> 49.038462 | F9: =IF(Table9[[#This Row],[AvgScore100]]>=80,"Low",IF(Table9[[#This Row],[AvgScore100]]>=70,"Medium","High")) -> Medium
A19: SoftControl | B19: AvgScore100
A20: Role Modelling | B20: =IFERROR(ROUND(AVERAGEIF(Responses!$D:$D, A2, Responses!$F:$F), 0), "") -> 75
A21: Discussability | B21: =IFERROR(ROUND(AVERAGEIF(Responses!$D:$D, A3, Responses!$F:$F), 0), "") -> 78
A22: Achievability | B22: =IFERROR(ROUND(AVERAGEIF(Responses!$D:$D, A4, Responses!$F:$F), 0), "") -> 72
A23: Enforcement | B23: =IFERROR(ROUND(AVERAGEIF(Responses!$D:$D, A5, Responses!$F:$F), 0), "") -> 75
A24: Clarity | B24: =IFERROR(ROUND(AVERAGEIF(Responses!$D:$D, A6, Responses!$F:$F), 0), "") -> 75
A25: Transparency | B25: =IFERROR(ROUND(AVERAGEIF(Responses!$D:$D, A7, Responses!$F:$F), 0), "") -> 75
A26: Commitment | B26: =IFERROR(ROUND(AVERAGEIF(Responses!$D:$D, A8, Responses!$F:$F), 0), "") -> 74
A27: Call Someone to Account | B27: =IFERROR(ROUND(AVERAGEIF(Responses!$D:$D, A9, Responses!$F:$F), 0), "") -> 70

Sheet SurveyForm
A1: Respondent ID | B1: R030
A2: Function | B2: Finance
A4: RespondentID | B4: QuestionID | C4: Question Text | D4: Response (user selects) | E4: Score_5 | F4: Score_100 | G4: SoftControl
A5: =$B$1 -> R030 | B5: {=INDEX(FinalQuestions!$A:$A, ROW()-3)} -> Q001 | C5: {=INDEX(FinalQuestions!$B:$B, ROW()-3)} -> I believe that my leaders and senior managers consistently act as positive role models, also when they are under time pressure or facing difficult trade‑offs. | D5: Agree | E5: =IF(D5="","",CHOOSE(MATCH(D5,{"Strongly Agree","Agree","Neutral","Disagree","Strongly Disagree"},0),5,4,3,2,1)) -> 4 | F5: =IF(E5="","",E5*20) -> 80 | G5: =_xlfn.XLOOKUP(B5,FinalQuestions!$A:$A,FinalQuestions!$C:$C,"") -> Role Modelling
A6: =$B$1 -> R030 | B6: {=INDEX(FinalQuestions!$A:$A, ROW()-3)} -> Q002 | C6: {=INDEX(FinalQuestions!$B:$B, ROW()-3)} -> Leaders openly emphasize the importance of doing things the right way, even under time pressure | D6: Agree | E6: =IF(D6="","",CHOOSE(MATCH(D6,{"Strongly Agree","Agree","Neutral","Disagree","Strongly Disagree"},0),5,4,3,2,1)) -> 4 | F6: =IF(E6="","",E6*20) -> 80 | G6: =_xlfn.XLOOKUP(B6,FinalQuestions!$A:$A,FinalQuestions!$C:$C,"") -> Role Modelling
A7: =$B$1 -> R030 | B7: {=INDEX(FinalQuestions!$A:$A, ROW()-3)} -> Q003 | C7: {=INDEX(FinalQuestions!$B:$B, ROW()-3)} -> All the seniors encourage employees to identify, escalate and report all the concerns in a timely manner | D7: Agree | E7: =IF(D7="","",CHOOSE(MATCH(D7,{"Strongly Agree","Agree","Neutral","Disagree","Strongly Disagree"},0),5,4,3,2,1)) -> 4 | F7: =IF(E7="","",E7*20) -> 80 | G7: =_xlfn.XLOOKUP(B7,FinalQuestions!$A:$A,FinalQuestions!$C:$C,"") -> Role Modelling
A8: =$B$1 -> R030 | B8: {=INDEX(FinalQuestions!$A:$A, ROW()-3)} -> Q004 | C8: {=INDEX(FinalQuestions!$B:$B, ROW()-3)} -> When decisions are made by leaders, potential and long-term implications are usually considered. | D8: Agree | E8: =IF(D8="","",CHOOSE(MATCH(D8,{"Strongly Agree","Agree","Neutral","Disagree","Strongly Disagree"},0),5,4,3,2,1)) -> 4 | F8: =IF(E8="","",E8*20) -> 80 | G8: =_xlfn.XLOOKUP(B8,FinalQuestions!$A:$A,FinalQuestions!$C:$C,"") -> Role Modelling
A9: =$B$1 -> R030 | B9: {=INDEX(FinalQuestions!$A:$A, ROW()-3)} -> Q005 | C9: {=INDEX(FinalQuestions!$B:$B, ROW()-3)} -> Differences of opinion are respected during discussions about judgments or decisions | D9: Agree | E9: =IF(D9="","",CHOOSE(MATCH(D9,{"Strongly Agree","Agree","Neutral","Disagree","Strongly Disagree"},0),5,4,3,2,1)) -> 4 | F9: =IF(E9="","",E9*20) -> 80 | G9: =_xlfn.XLOOKUP(B9,FinalQuestions!$A:$A,FinalQuestions!$C:$C,"") -> Discussability
A10: =$B$1 -> R030 | B10: {=INDEX(FinalQuestions!$A:$A, ROW()-3)} -> Q006 | C10: {=INDEX(FinalQuestions!$B:$B, ROW()-3)} -> I can openly raise concerns without fear of negative consequences | D10: Agree | E10: =IF(D10="","",CHOOSE(MATCH(D10,{"Strongly Agree","Agree","Neutral","Disagree","Strongly Disagree"},0),5,4,3,2,1)) -> 4 | F10: =IF(E10="","",E10*20) -> 80 | G10: =_xlfn.XLOOKUP(B10,FinalQuestions!$A:$A,FinalQuestions!$C:$C,"") -> Discussability
A11: =$B$1 -> R030 | B11: {=INDEX(FinalQuestions!$A:$A, ROW()-3)} -> Q007 | C11: {=INDEX(FinalQuestions!$B:$B, ROW()-3)} -> Colleagues respond constructively when mistakes or concerns are raised management. | D11: Agree | E11: =IF(D11="","",CHOOSE(MATCH(D11,{"Strongly Agree","Agree","Neutral","Disagree","Strongly Disagree"},0),5,4,3,2,1)) -> 4 | F11: =IF(E11="","",E11*20) -> 80 | G11: =_xlfn.XLOOKUP(B11,FinalQuestions!$A:$A,FinalQuestions!$C:$C,"") -> Discussability
A12: =$B$1 -> R030 | B12: {=INDEX(FinalQuestions!$A:$A, ROW()-3)} -> Q008 | C12: {=INDEX(FinalQuestions!$B:$B, ROW()-3)} -> I feel comfortable escalating issues to Risk Management / Ethics & Independence / DPP when needed | D12: Agree | E12: =IF(D12="","",CHOOSE(MATCH(D12,{"Strongly Agree","Agree","Neutral","Disagree","Strongly Disagree"},0),5,4,3,2,1)) -> 4 | F12: =IF(E12="","",E12*20) -> 80 | G12: =_xlfn.XLOOKUP(B12,FinalQuestions!$A:$A,FinalQuestions!$C:$C,"") -> Discussability
A13: =$B$1 -> R030 | B13: {=INDEX(FinalQuestions!$A:$A, ROW()-3)} -> Q009 | C13: {=INDEX(FinalQuestions!$B:$B, ROW()-3)} -> I have received enough training to handle job‑related challenges effectively. | D13: Agree | E13: =IF(D13="","",CHOOSE(MATCH(D13,{"Strongly Agree","Agree","Neutral","Disagree","Strongly Disagree"},0),5,4,3,2,1)) -> 4 | F13: =IF(E13="","",E13*20) -> 80 | G13: =_xlfn.XLOOKUP(B13,FinalQuestions!$A:$A,FinalQuestions!$C:$C,"") -> Achievability
A14: =$B$1 -> R030 | B14: {=INDEX(FinalQuestions!$A:$A, ROW()-3)} -> Q010 | C14: {=INDEX(FinalQuestions!$B:$B, ROW()-3)} -> Within my team or department people have enough time and resources to do their job without taking unacceptable risks | D14: Agree | E14: =IF(D14="","",CHOOSE(MATCH(D14,{"Strongly Agree","Agree","Neutral","Disagree","Strongly Disagree"},0),5,4,3,2,1)) -> 4 | F14: =IF(E14="","",E14*20) -> 80 | G14: =_xlfn.XLOOKUP(B14,FinalQuestions!$A:$A,FinalQuestions!$C:$C,"") -> Achievability
A15: =$B$1 -> R030 | B15: {=INDEX(FinalQuestions!$A:$A, ROW()-3)} -> Q011 | C15: {=INDEX(FinalQuestions!$B:$B, ROW()-3)} -> People set targets that are achievable without compromising risk management policies, guidelines and procedures. | D15: Agree | E15: =IF(D15="","",CHOOSE(MATCH(D15,{"Strongly Agree","Agree","Neutral","Disagree","Strongly Disagree"},0),5,4,3,2,1)) -> 4 | F15: =IF(E15="","",E15*20) -> 80 | G15: =_xlfn.XLOOKUP(B15,FinalQuestions!$A:$A,FinalQuestions!$C:$C,"") -> Achievability
A16: =$B$1 -> R030 | B16: {=INDEX(FinalQuestions!$A:$A, ROW()-3)} -> Q012 | C16: {=INDEX(FinalQuestions!$B:$B, ROW()-3)} -> People visibly consider potential risks when making strategic decisions | D16: Agree | E16: =IF(D16="","",CHOOSE(MATCH(D16,{"Strongly Agree","Agree","Neutral","Disagree","Strongly Disagree"},0),5,4,3,2,1)) -> 4 | F16: =IF(E16="","",E16*20) -> 80 | G16: =_xlfn.XLOOKUP(B16,FinalQuestions!$A:$A,FinalQuestions!$C:$C,"") -> Achievability
... A36: =$B$1 -> R030 | B36: {=INDEX(FinalQuestions!$A:$A, ROW()-3)} -> Q032 | C36: {=INDEX(FinalQuestions!$B:$B, ROW()-3)} -> Team members are held to the same behavioral standards, no matter who they are. | D36: Strongly Agree | E36: =IF(D36="","",CHOOSE(MATCH(D36,{"Strongly Agree","Agree","Neutral","Disagree","Strongly Disagree"},0),5,4,3,2,1)) -> 5 | F36: =IF(E36="","",E36*20) -> 100 | G36: =_xlfn.XLOOKUP(B36,FinalQuestions!$A:$A,FinalQuestions!$C:$C,"") -> Call someone to account

Sheet Functions
A1: RespondentID | B1: Function
A2: R001 | B2: HR
A3: R002 | B3: Finance
A4: R003 | B4: HR
A5: R004 | B5: Operations
A6: R005 | B6: Operations
A7: R006 | B7: Audit
A8: R007 | B8: Finance
A9: R008 | B9: HR
A10: R009 | B10: Audit
A11: R010 | B11: IT
A12: R011 | B12: Sales
... A26: R025 | B26: Finance

Sheet Dimension Sheet
A1: Dimension | B1: AvgScore_100 | C1: Favorable% | D1: Unfavorable% | E1: Neutral% | F1: People_Unfavorable | G1: Total_Responses
A2: =_xlfn.XLOOKUP(Table7[[#This Row],[QuestionID]], FinalQuestions!$A:$A, FinalQuestions!$D:$D,"") -> Leadership Example‑Setting in Risk Management | B2: =IFERROR(ROUND(AVERAGEIFS(Responses!$F:$F,Responses!$H:$H,$A2),0),0) -> 71 | C2: =IFERROR(SUMIFS(Responses!$G:$G,Responses!$H:$H,$A2)/COUNTIFS(Responses!$H:$H,$A2),0) -> 0.46153846 | D2: =IFERROR((COUNTIFS(Responses!$H:$H,$A2,Responses!$C:$C,"Disagree")+COUNTIFS(Responses!$H:$H,$A2,Responses!$C:$C,"Strongly Disagree"))/COUNTIFS(Responses!$H:$H,$A2),0) -> 0.11538462 | E2: =1-C2-D2 -> 0.42307692 | F2: {=_xlfn.LET(_xlpm.dim,$A2,_xlpm.bad,_xlfn._xlws.FILTER(Responses!$A:$A,(Responses!$H:$H=_xlpm.dim)*((Responses!$C:$C="Disagree")+(Responses!$C:$C="Strongly Disagree"))),COUNTA(_xlfn.UNIQUE(_xlpm.bad)))} -> 3 | G2: =COUNTIFS(Responses!$H:$H,$A2) -> 26
A3: =_xlfn.XLOOKUP(Table7[[#This Row],[QuestionID]], FinalQuestions!$A:$A, FinalQuestions!$D:$D,"") -> Executive Commitment to Risk Culture | B3: =IFERROR(ROUND(AVERAGEIFS(Responses!$F:$F,Responses!$H:$H,$A3),0),0) -> 76 | C3: =IFERROR(SUMIFS(Responses!$G:$G,Responses!$H:$H,$A3)/COUNTIFS(Responses!$H:$H,$A3),0) -> 0.61538462 | D3: =IFERROR((COUNTIFS(Responses!$H:$H,$A3,Responses!$C:$C,"Disagree")+COUNTIFS(Responses!$H:$H,$A3,Responses!$C:$C,"Strongly Disagree"))/COUNTIFS(Responses!$H:$H,$A3),0) -> 0.076923077 | E3: =1-C3-D3 -> 0.30769231 | F3: {=_xlfn.LET(_xlpm.dim,$A3,_xlpm.bad,_xlfn._xlws.FILTER(Responses!$A:$A,(Responses!$H:$H=_xlpm.dim)*((Responses!$C:$C="Disagree")+(Responses!$C:$C="Strongly Disagree"))),COUNTA(_xlfn.UNIQUE(_xlpm.bad)))} -> 2 | G3: =COUNTIFS(Responses!$H:$H,$A3) -> 26
A4: =_xlfn.XLOOKUP(Table7[[#This Row],[QuestionID]], FinalQuestions!$A:$A, FinalQuestions!$D:$D,"") -> Leadership Encouragement to Escalate Risks | B4: =IFERROR(ROUND(AVERAGEIFS(Responses!$F:$F,Responses!$H:$H,$A4),0),0) -> 82 | C4: =IFERROR(SUMIFS(Responses!$G:$G,Responses!$H:$H,$A4)/COUNTIFS(Responses!$H:$H,$A4),0) -> 0.73076923 | D4: =IFERROR((COUNTIFS(Responses!$H:$H,$A4,Responses!$C:$C,"Disagree")+COUNTIFS(Responses!$H:$H,$A4,Responses!$C:$C,"Strongly Disagree"))/COUNTIFS(Responses!$H:$H,$A4),0) -> 0 | E4: =1-C4-D4 -> 0.26923077 | F4: {=_xlfn.LET(_xlpm.dim,$A4,_xlpm.bad,_xlfn._xlws.FILTER(Responses!$A:$A,(Responses!$H:$H=_xlpm.dim)*((Responses!$C:$C="Disagree")+(Responses!$C:$C="Strongly Disagree"))),COUNTA(_xlfn.UNIQUE(_xlpm.bad)))} -> 1 | G4: =COUNTIFS(Responses!$H:$H,$A4) -> 26
A5: =_xlfn.XLOOKUP(Table7[[#This Row],[QuestionID]], FinalQuestions!$A:$A, FinalQuestions!$D:$D,"") -> Long-Term Decision Awareness | B5: =IFERROR(ROUND(AVERAGEIFS(Responses!$F:$F,Responses!$H:$H,$A5),0),0) -> 73 | C5: =IFERROR(SUMIFS(Responses!$G:$G,Responses!$H:$H,$A5)/COUNTIFS(Responses!$H:$H,$A5),0) -> 0.53846154 | D5: =IFERROR((COUNTIFS(Responses!$H:$H,$A5,Responses!$C:$C,"Disagree")+COUNTIFS(Responses!$H:$H,$A5,Responses!$C:$C,"Strongly Disagree"))/COUNTIFS(Responses!$H:$H,$A5),0) -> 0.15384615 | E5: =1-C5-D5 -> 0.30769231 | F5: {=_xlfn.LET(_xlpm.dim,$A5,_xlpm.bad,_xlfn._xlws.FILTER(Responses!$A:$A,(Responses!$H:$H=_xlpm.dim)*((Responses!$C:$C="Disagree")+(Responses!$C:$C="Strongly Disagree"))),COUNTA(_xlfn.UNIQUE(_xlpm.bad)))} -> 4 | G5: =COUNTIFS(Responses!$H:$H,$A5) -> 26
A6: =_xlfn.XLOOKUP(Table7[[#This Row],[QuestionID]], FinalQuestions!$A:$A, FinalQuestions!$D:$D,"") -> Openness to Discussions | B6: =IFERROR(ROUND(AVERAGEIFS(Responses!$F:$F,Responses!$H:$H,$A6),0),0) -> 72 | C6: =IFERROR(SUMIFS(Responses!$G:$G,Responses!$H:$H,$A6)/COUNTIFS(Responses!$H:$H,$A6),0) -> 0.5 | D6: =IFERROR((COUNTIFS(Responses!$H:$H,$A6,Responses!$C:$C,"Disagree")+COUNTIFS(Responses!$H:$H,$A6,Responses!$C:$C,"Strongly Disagree"))/COUNTIFS(Responses!$H:$H,$A6),0) -> 0.11538462 | E6: =1-C6-D6 -> 0.38461538 | F6: {=_xlfn.LET(_xlpm.dim,$A6,_xlpm.bad,_xlfn._xlws.FILTER(Responses!$A:$A,(Responses!$H:$H=_xlpm.dim)*((Responses!$C:$C="Disagree")+(Responses!$C:$C="Strongly Disagree"))),COUNTA(_xlfn.UNIQUE(_xlpm.bad)))} -> 3 | G6: =COUNTIFS(Responses!$H:$H, $A3) -> 26
A7: =_xlfn.XLOOKUP(Table7[[#This Row],[QuestionID]], FinalQuestions!$A:$A, FinalQuestions!$D:$D,"") -> Access to Guidance | B7: =IFERROR(ROUND(AVERAGEIFS(Responses!$F:$F,Responses!$H:$H,$A7),0),0) -> 78 | C7: =IFERROR(SUMIFS(Responses!$G:$G,Responses!$H:$H,$A7)/COUNTIFS(Responses!$H:$H,$A7),0) -> 0.53846154 | D7: =IFERROR((COUNTIFS(Responses!$H:$H,$A7,Responses!$C:$C,"Disagree")+COUNTIFS(Responses!$H:$H,$A7,Responses!$C:$C,"Strongly Disagree"))/COUNTIFS(Responses!$H:$H,$A7),0) -> 0.038461538 | E7: =1-C7-D7 -> 0.42307692 | F7: {=_xlfn.LET(_xlpm.dim,$A7,_xlpm.bad,_xlfn._xlws.FILTER(Responses!$A:$A,(Responses!$H:$H=_xlpm.dim)*((Responses!$C:$C="Disagree")+(Responses!$C:$C="Strongly Disagree"))),COUNTA(_xlfn.UNIQUE(_xlpm.bad)))} -> 1 | G7: =COUNTIFS(Responses!$H:$H, $A4) -> 26
A8: =_xlfn.XLOOKUP(Table7[[#This Row],[QuestionID]], FinalQuestions!$A:$A, FinalQuestions!$D:$D,"") -> Openness to Sharing Opinions | B8: =IFERROR(ROUND(AVERAGEIFS(Responses!$F:$F,Responses!$H:$H,$A8),0),0) -> 82 | C8: =IFERROR(SUMIFS(Responses!$G:$G,Responses!$H:$H,$A8)/COUNTIFS(Responses!$H:$H,$A8),0) -> 0.73076923 | D8: =IFERROR((COUNTIFS(Responses!$H:$H,$A8,Responses!$C:$C,"Disagree")+COUNTIFS(Responses!$H:$H,$A8,Responses!$C:$C,"Strongly Disagree"))/COUNTIFS(Responses!$H:$H,$A8),0) -> 0.038461538 | E8: =1-C8-D8 -> 0.23076923 | F8: {=_xlfn.LET(_xlpm.dim,$A8,_xlpm.bad,_xlfn._xlws.FILTER(Responses!$A:$A,(Responses!$H:$H=_xlpm.dim)*((Responses!$C:$C="Disagree")+(Responses!$C:$C="Strongly Disagree"))),COUNTA(_xlfn.UNIQUE(_xlpm.bad)))} -> 1 | G8: =COUNTIFS(Responses!$H:$H, $A5) -> 26
A9: =_xlfn.XLOOKUP(Table7[[#This Row],[QuestionID]], FinalQuestions!$A:$A, FinalQuestions!$D:$D,"") -> Comfort in Reporting Risk Dilemmas | B9: =IFERROR(ROUND(AVERAGEIFS(Responses!$F:$F,Responses!$H:$H,$A9),0),0) -> 80 | C9: =IFERROR(SUMIFS(Responses!$G:$G,Responses!$H:$H,$A9)/COUNTIFS(Responses!$H:$H,$A9),0) -> 0.69230769 | D9: =IFERROR((COUNTIFS(Responses!$H:$H,$A9,Responses!$C:$C,"Disagree")+COUNTIFS(Responses!$H:$H,$A9,Responses!$C:$C,"Strongly Disagree"))/COUNTIFS(Responses!$H:$H,$A9),0) -> 0.076923077 | E9: =1-C9-D9 -> 0.23076923 | F9: {=_xlfn.LET(_xlpm.dim,$A9,_xlpm.bad,_xlfn._xlws.FILTER(Responses!$A:$A,(Responses!$H:$H=_xlpm.dim)*((Responses!$C:$C="Disagree")+(Responses!$C:$C="Strongly Disagree"))),COUNTA(_xlfn.UNIQUE(_xlpm.bad)))} -> 2 | G9: =COUNTIFS(Responses!$H:$H, $A6) -> 26
A10: =_xlfn.XLOOKUP(Table7[[#This Row],[QuestionID]], FinalQuestions!$A:$A, FinalQuestions!$D:$D,"") -> Adequacy of Risk Management Training | B10: =IFERROR(ROUND(AVERAGEIFS(Responses!$F:$F,Responses!$H:$H,$A10),0),0) -> 75 | C10: =IFERROR(SUMIFS(Responses!$G:$G,Responses!$H:$H,$A10)/COUNTIFS(Responses!$H:$H,$A10),0) -> 0.57692308 | D10: =IFERROR((COUNTIFS(Responses!$H:$H,$A10,Responses!$C:$C,"Disagree")+COUNTIFS(Responses!$H:$H,$A10,Responses!$C:$C,"Strongly Disagree"))/COUNTIFS(Responses!$H:$H,$A10),0) -> 0.23076923 | E10: =1-C10-D10 -> 0.19230769 | F10: {=_xlfn.LET(_xlpm.dim,$A10,_xlpm.bad,_xlfn._xlws.FILTER(Responses!$A:$A,(Responses!$H:$H=_xlpm.dim)*((Responses!$C:$C="Disagree")+(Responses!$C:$C="Strongly Disagree"))),COUNTA(_xlfn.UNIQUE(_xlpm.bad)))} -> 6 | G10: =COUNTIFS(Responses!$H:$H, $A7) -> 26
A11: =_xlfn.XLOOKUP(Table7[[#This Row],[QuestionID]], FinalQuestions!$A:$A, FinalQuestions!$D:$D,"") -> Workload Balance & Resource Sufficiency | B11: =IFERROR(ROUND(AVERAGEIFS(Responses!$F:$F,Responses!$H:$H,$A11),0),0) -> 72 | C11: =IFERROR(SUMIFS(Responses!$G:$G,Responses!$H:$H,$A11)/COUNTIFS(Responses!$H:$H,$A11),0) -> 0.5 | D11: =IFERROR((COUNTIFS(Responses!$H:$H,$A11,Responses!$C:$C,"Disagree")+COUNTIFS(Responses!$H:$H,$A11,Responses!$C:$C,"Strongly Disagree"))/COUNTIFS(Responses!$H:$H,$A11),0) -> 0.11538462 | E11: =1-C11-D11 -> 0.38461538 | F11: {=_xlfn.LET(_xlpm.dim,$A11,_xlpm.bad,_xlfn._xlws.FILTER(Responses!$A:$A,(Responses!$H:$H=_xlpm.dim)*((Responses!$C:$C="Disagree")+(Responses!$C:$C="Strongly Disagree"))),COUNTA(_xlfn.UNIQUE(_xlpm.bad)))} -> 3 | G11: =COUNTIFS(Responses!$H:$H, $A8) -> 26
A12: =_xlfn.XLOOKUP(Table7[[#This Row],[QuestionID]], FinalQuestions!$A:$A, FinalQuestions!$D:$D,"") -> Realistic Target Setting | B12: =IFERROR(ROUND(AVERAGEIFS(Responses!$F:$F,Responses!$H:$H,$A12),0),0) -> 74 | C12: =IFERROR(SUMIFS(Responses!$G:$G,Responses!$H:$H,$A12)/COUNTIFS(Responses!$H:$H,$A12),0) -> 0.61538462 | D12: =IFERROR((COUNTIFS(Responses!$H:$H,$A12,Responses!$C:$C,"Disagree")+COUNTIFS(Responses!$H:$H,$A12,Responses!$C:$C,"Strongly Disagree"))/COUNTIFS(Responses!$H:$H,$A12),0) -> 0.15384615 | E12: =1-C12-D12 -> 0.23076923 | F12: {=_xlfn.LET(_xlpm.dim,$A12,_xlpm.bad,_xlfn._xlws.FILTER(Responses!$A:$A,(Responses!$H:$H=_xlpm.dim)*((Responses!$C:$C="Disagree")+(Responses!$C:$C="Strongly Disagree"))),COUNTA(_xlfn.UNIQUE(_xlpm.bad)))} -> 4 | G12: =COUNTIFS(Responses!$H:$H, $A9) -> 26
A13: =_xlfn.XLOOKUP(Table7[[#This Row],[QuestionID]], FinalQuestions!$A:$A, FinalQuestions!$D:$D,"") -> Risk Insight in Decision Making | B13: =IFERROR(ROUND(AVERAGEIFS(Responses!$F:$F,Responses!$H:$H,$A13),0),0) -> 68 | C13: =IFERROR(SUMIFS(Responses!$G:$G,Responses!$H:$H,$A13)/COUNTIFS(Responses!$H:$H,$A13),0) -> 0.46153846 | D13: =IFERROR((COUNTIFS(Responses!$H:$H,$A13,Responses!$C:$C,"Disagree")+COUNTIFS(Responses!$H:$H,$A13,Responses!$C:$C,"Strongly Disagree"))/COUNTIFS(Responses!$H:$H,$A13),0) -> 0.26923077 | E13: =1-C13-D13 -> 0.26923077 | F13: {=_xlfn.LET(_xlpm.dim,$A13,_xlpm.bad,_xlfn._xlws.FILTER(Responses!$A:$A,(Responses!$H:$H=_xlpm.dim)*((Responses!$C:$C="Disagree")+(Responses!$C:$C="Strongly Disagree"))),COUNTA(_xlfn.UNIQUE(_xlpm.bad)))} -> 7 | G13: =COUNTIFS(Responses!$H:$H, $A10) -> 26
A14: =_xlfn.XLOOKUP(Table7[[#This Row],[QuestionID]], FinalQuestions!$A:$A, FinalQuestions!$D:$D,"") -> Learning Culture from Non‑Compliance Cases | B14: =IFERROR(ROUND(AVERAGEIFS(Responses!$F:$F,Responses!$H:$H,$A14),0),0) -> 70 | C14: =IFERROR(SUMIFS(Responses!$G:$G,Responses!$H:$H,$A14)/COUNTIFS(Responses!$H:$H,$A14),0) -> 0.38461538 | D14: =IFERROR((COUNTIFS(Responses!$H:$H,$A14,Responses!$C:$C,"Disagree")+COUNTIFS(Responses!$H:$H,$A14,Responses!$C:$C,"Strongly Disagree"))/COUNTIFS(Responses!$H:$H,$A14),0) -> 0.15384615 | E14: =1-C14-D14 -> 0.46153846 | F14: {=_xlfn.LET(_xlpm.dim,$A14,_xlpm.bad,_xlfn._xlws.FILTER(Responses!$A:$A,(Responses!$H:$H=_xlpm.dim)*((Responses!$C:$C="Disagree")+(Responses!$C:$C="Strongly Disagree"))),COUNTA(_xlfn.UNIQUE(_xlpm.bad)))} -> 4 | G14: =COUNTIFS(Responses!$H:$H, $A11) -> 26
A15: =_xlfn.XLOOKUP(Table7[[#This Row],[QuestionID]], FinalQuestions!$A:$A, FinalQuestions!$D:$D,"") -> Organizational View on Risk Culture | B15: =IFERROR(ROUND(AVERAGEIFS(Responses!$F:$F,Responses!$H:$H,$A15),0),0) -> 84 | C15: =IFERROR(SUMIFS(Responses!$G:$G,Responses!$H:$H,$A15)/COUNTIFS(Responses!$H:$H,$A15),0) -> 0.73076923 | D15: =IFERROR((COUNTIFS(Responses!$H:$H,$A15,Responses!$C:$C,"Disagree")+COUNTIFS(Responses!$H:$H,$A15,Responses!$C:$C,"Strongly Disagree"))/COUNTIFS(Responses!$H:$H,$A15),0) -> 0 | E15: =1-C15-D15 -> 0.26923077 | F15: {=_xlfn.LET(_xlpm.dim,$A15,_xlpm.bad,_xlfn._xlws.FILTER(Responses!$A:$A,(Responses!$H:$H=_xlpm.dim)*((Responses!$C:$C="Disagree")+(Responses!$C:$C="Strongly Disagree"))),COUNTA(_xlfn.UNIQUE(_xlpm.bad)))} -> 1 | G15: =COUNTIFS(Responses!$H:$H, $A12) -> 26
A16: =_xlfn.XLOOKUP(Table7[[#This Row],[QuestionID]], FinalQuestions!$A:$A, FinalQuestions!$D:$D,"") -> Compliance Recognition & enforcement | B16: =IFERROR(ROUND(AVERAGEIFS(Responses!$F:$F,Responses!$H:$H,$A16),0),0) -> 78 | C16: =IFERROR(SUMIFS(Responses!$G:$G,Responses!$H:$H,$A16)/COUNTIFS(Responses!$H:$H,$A16),0) -> 0.65384615 | D16: =IFERROR((COUNTIFS(Responses!$H:$H,$A16,Responses!$C:$C,"Disagree")+COUNTIFS(Responses!$H:$H,$A16,Responses!$C:$C,"Strongly Disagree"))/COUNTIFS(Responses!$H:$H,$A16),0) -> 0.11538462 | E16: =1-C16-D16 -> 0.23076923 | F16: {=_xlfn.LET(_xlpm.dim,$A16,_xlpm.bad,_xlfn._xlws.FILTER(Responses!$A:$A,(Responses!$H:$H=_xlpm.dim)*((Responses!$C:$C="Disagree")+(Responses!$C:$C="Strongly Disagree"))),COUNTA(_xlfn.UNIQUE(_xlpm.bad)))} -> 3 | G16: =COUNTIFS(Responses!$H:$H, $A13) -> 26
A17: =_xlfn.XLOOKUP(Table7[[#This Row],[QuestionID]], FinalQuestions!$A:$A, FinalQuestions!$D:$D,"") -> Sense of Ownership | B17: =IFERROR(ROUND(AVERAGEIFS(Responses!$F:$F,Responses!$H:$H,$A17),0),0) -> 68 | C17: =IFERROR(SUMIFS(Responses!$G:$G,Responses!$H:$H,$A17)/COUNTIFS(Responses!$H:$H,$A17),0) -> 0.46153846 | D17: =IFERROR((COUNTIFS(Responses!$H:$H,$A17,Responses!$C:$C,"Disagree")+COUNTIFS(Responses!$H:$H,$A17,Responses!$C:$C,"Strongly Disagree"))/COUNTIFS(Responses!$H:$H,$A17),0) -> 0.26923077 | E17: =1-C17-D17 -> 0.26923077 | F17: {=_xlfn.LET(_xlpm.dim,$A17,_xlpm.bad,_xlfn._xlws.FILTER(Responses!$A:$A,(Responses!$H:$H=_xlpm.dim)*((Responses!$C:$C="Disagree")+(Responses!$C:$C="Strongly Disagree"))),COUNTA(_xlfn.UNIQUE(_xlpm.bad)))} -> 7 | G17: =COUNTIFS(Responses!$H:$H, $A14) -> 26
... A33: =_xlfn.XLOOKUP(Table7[[#This Row],[QuestionID]], FinalQuestions!$A:$A, FinalQuestions!$D:$D,"") -> Consistency of Conduct Enforcement | B33: =IFERROR(ROUND(AVERAGEIFS(Responses!$F:$F,Responses!$H:$H,$A33),0),0) -> 72 | C33: =IFERROR(SUMIFS(Responses!$G:$G,Responses!$H:$H,$A33)/COUNTIFS(Responses!$H:$H,$A33),0) -> 0.53846154 | D33: =IFERROR((COUNTIFS(Responses!$H:$H,$A33,Responses!$C:$C,"Disagree")+COUNTIFS(Responses!$H:$H,$A33,Responses!$C:$C,"Strongly Disagree"))/COUNTIFS(Responses!$H:$H,$A33),0) -> 0.11538462 | E33: =1-C33-D33 -> 0.34615385 | F33: {=_xlfn.LET(_xlpm.dim,$A33,_xlpm.bad,_xlfn._xlws.FILTER(Responses!$A:$A,(Responses!$H:$H=_xlpm.dim)*((Responses!$C:$C="Disagree")+(Responses!$C:$C="Strongly Disagree"))),COUNTA(_xlfn.UNIQUE(_xlpm.bad)))} -> 3 | G33: =COUNTIFS(Responses!$H:$H, $A30) -> 26
A37: =INDEX($A$2:$A$33, MATCH(SMALL($B$2:$B$33,1), $B$2:$B$33, 0)) -> Peer to peer Accountability
A38: =INDEX($A$2:$A$33,MATCH(SMALL($B$2:$B$33,3),$B$2:$B$33,0)) -> Risk Insight in Decision Making
A49: ="Top risk root-cause areas include: " & INDEX($A$2:$A$33,MATCH(SMALL($B$2:$B$33,1),$B$2:$B$33,0))& "," & INDEX($A$2:$A$33,MATCH(SMALL($B$2:$B$33,2),$B$2:$B$33,0))& ",and " & INDEX($A$2:$A$33,MATCH(SMALL($B$2:$B$33,3),$B$2:$B$33,0))& ". These are influenced by low favorable responses and require targeted interventions." -> Top risk root-cause areas include: Peer to peer Accountability ,Timely Resolution of Accountability Issues,and Risk Insight in Decision Making. These are influenced by low favorable responses and require targeted interventions.

Sheet Flagged_Qs
A1: QuestionID | B1: Flagged_RCI | C1: Favourable% | D1: Unfavourable%
A2: {=_xlfn._xlws.FILTER(FinalQuestions!$A$2:$A$198,FinalQuestions!$H$2:$H$198="Yes")} -> #VALUE! | B2: =IFERROR(ROUND(AVERAGEIFS(Responses!$F:$F,Responses!$B:$B,$A2),0),"") | C2: =IFERROR(AVERAGEIFS(Responses!$G:$G,Responses!$B:$B,$A2),0)*100 -> 0 | D2: =IFERROR((COUNTIFS(Responses!$B:$B,$A2,Responses!$C:$C,"Disagree")+COUNTIFS(Responses!$B:$B,$A2,Responses!$C:$C,"Strongly Disagree"))/COUNTIF(Responses!$B:$B,$A2),0)*100 -> 0
B3: =IFERROR(ROUND(AVERAGEIFS(Responses!$F:$F,Responses!$B:$B,$A3),0),"") | C3: =IFERROR(AVERAGEIFS(Responses!$G:$G,Responses!$B:$B,$A3),0)*100 -> 0 | D3: =IFERROR((COUNTIFS(Responses!$B:$B,$A3,Responses!$C:$C,"Disagree")+COUNTIFS(Responses!$B:$B,$A3,Responses!$C:$C,"Strongly Disagree"))/COUNTIF(Responses!$B:$B,$A3),0)*100 -> 0
B4: =IFERROR(ROUND(AVERAGEIFS(Responses!$F:$F,Responses!$B:$B,$A4),0),"") | C4: =IFERROR(AVERAGEIFS(Responses!$G:$G,Responses!$B:$B,$A4),0)*100 -> 0 | D4: =IFERROR((COUNTIFS(Responses!$B:$B,$A4,Responses!$C:$C,"Disagree")+COUNTIFS(Responses!$B:$B,$A4,Responses!$C:$C,"Strongly Disagree"))/COUNTIF(Responses!$B:$B,$A4),0)*100 -> 0
B5: =IFERROR(ROUND(AVERAGEIFS(Responses!$F:$F,Responses!$B:$B,$A5),0),"") | C5: =IFERROR(AVERAGEIFS(Responses!$G:$G,Responses!$B:$B,$A5),0)*100 -> 0 | D5: =IFERROR((COUNTIFS(Responses!$B:$B,$A5,Responses!$C:$C,"Disagree")+COUNTIFS(Responses!$B:$B,$A5,Responses!$C:$C,"Strongly Disagree"))/COUNTIF(Responses!$B:$B,$A5),0)*100 -> 0
B6: =IFERROR(ROUND(AVERAGEIFS(Responses!$F:$F,Responses!$B:$B,$A6),0),"") | C6: =IFERROR(AVERAGEIFS(Responses!$G:$G,Responses!$B:$B,$A6),0)*100 -> 0 | D6: =IFERROR((COUNTIFS(Responses!$B:$B,$A6,Responses!$C:$C,"Disagree")+COUNTIFS(Responses!$B:$B,$A6,Responses!$C:$C,"Strongly Disagree"))/COUNTIF(Responses!$B:$B,$A6),0)*100 -> 0
B7: =IFERROR(ROUND(AVERAGEIFS(Responses!$F:$F,Responses!$B:$B,$A7),0),"") | C7: =IFERROR(AVERAGEIFS(Responses!$G:$G,Responses!$B:$B,$A7),0)*100 -> 0 | D7: =IFERROR((COUNTIFS(Responses!$B:$B,$A7,Responses!$C:$C,"Disagree")+COUNTIFS(Responses!$B:$B,$A7,Responses!$C:$C,"Strongly Disagree"))/COUNTIF(Responses!$B:$B,$A7),0)*100 -> 0
B8: =IFERROR(ROUND(AVERAGEIFS(Responses!$F:$F,Responses!$B:$B,$A8),0),"") | C8: =IFERROR(AVERAGEIFS(Responses!$G:$G,Responses!$B:$B,$A8),0)*100 -> 0 | D8: =IFERROR((COUNTIFS(Responses!$B:$B,$A8,Responses!$C:$C,"Disagree")+COUNTIFS(Responses!$B:$B,$A8,Responses!$C:$C,"Strongly Disagree"))/COUNTIF(Responses!$B:$B,$A8),0)*100 -> 0
B9: =IFERROR(ROUND(AVERAGEIFS(Responses!$F:$F,Responses!$B:$B,$A9),0),"") | C9: =IFERROR(AVERAGEIFS(Responses!$G:$G,Responses!$B:$B,$A9),0)*100 -> 0 | D9: =IFERROR((COUNTIFS(Responses!$B:$B,$A9,Responses!$C:$C,"Disagree")+COUNTIFS(Responses!$B:$B,$A9,Responses!$C:$C,"Strongly Disagree"))/COUNTIF(Responses!$B:$B,$A9),0)*100 -> 0
B10: =IFERROR(ROUND(AVERAGEIFS(Responses!$F:$F,Responses!$B:$B,$A10),0),"") | C10: =IFERROR(AVERAGEIFS(Responses!$G:$G,Responses!$B:$B,$A10),0)*100 -> 0 | D10: =IFERROR((COUNTIFS(Responses!$B:$B,$A10,Responses!$C:$C,"Disagree")+COUNTIFS(Responses!$B:$B,$A10,Responses!$C:$C,"Strongly Disagree"))/COUNTIF(Responses!$B:$B,$A10),0)*100 -> 0
B11: =IFERROR(ROUND(AVERAGEIFS(Responses!$F:$F,Responses!$B:$B,$A11),0),"") | C11: =IFERROR(AVERAGEIFS(Responses!$G:$G,Responses!$B:$B,$A11),0)*100 -> 0 | D11: =IFERROR((COUNTIFS(Responses!$B:$B,$A11,Responses!$C:$C,"Disagree")+COUNTIFS(Responses!$B:$B,$A11,Responses!$C:$C,"Strongly Disagree"))/COUNTIF(Responses!$B:$B,$A11),0)*100 -> 0
B12: =IFERROR(ROUND(AVERAGEIFS(Responses!$F:$F,Responses!$B:$B,$A12),0),"") | C12: =IFERROR(AVERAGEIFS(Responses!$G:$G,Responses!$B:$B,$A12),0)*100 -> 0 | D12: =IFERROR((COUNTIFS(Responses!$B:$B,$A12,Responses!$C:$C,"Disagree")+COUNTIFS(Responses!$B:$B,$A12,Responses!$C:$C,"Strongly Disagree"))/COUNTIF(Responses!$B:$B,$A12),0)*100 -> 0
B13: =IFERROR(ROUND(AVERAGEIFS(Responses!$F:$F,Responses!$B:$B,$A13),0),"") | C13: =IFERROR(AVERAGEIFS(Responses!$G:$G,Responses!$B:$B,$A13),0)*100 -> 0 | D13: =IFERROR((COUNTIFS(Responses!$B:$B,$A13,Responses!$C:$C,"Disagree")+COUNTIFS(Responses!$B:$B,$A13,Responses!$C:$C,"Strongly Disagree"))/COUNTIF(Responses!$B:$B,$A13),0)*100 -> 0
B14: =IFERROR(ROUND(AVERAGEIFS(Responses!$F:$F,Responses!$B:$B,$A14),0),"") | C14: =IFERROR(AVERAGEIFS(Responses!$G:$G,Responses!$B:$B,$A14),0)*100 -> 0 | D14: =IFERROR((COUNTIFS(Responses!$B:$B,$A14,Responses!$C:$C,"Disagree")+COUNTIFS(Responses!$B:$B,$A14,Responses!$C:$C,"Strongly Disagree"))/COUNTIF(Responses!$B:$B,$A14),0)*100 -> 0
... B18: =IFERROR(ROUND(AVERAGEIFS(Responses!$F:$F,Responses!$B:$B,$A18),0),"") | C18: =IFERROR(AVERAGEIFS(Responses!$G:$G,Responses!$B:$B,$A18),0)*100 -> 0 | D18: =IFERROR((COUNTIFS(Responses!$B:$B,$A18,Responses!$C:$C,"Disagree")+COUNTIFS(Responses!$B:$B,$A18,Responses!$C:$C,"Strongly Disagree"))/COUNTIF(Responses!$B:$B,$A18),0)*100 -> 0

Sheet Recommendations
A1: SoftControl | B1: Recommendation | C1: How | D1: When
A2: Discussibility | B2: Run small-group listening meetings to hear concerns and ideas. | C2: Collect topics anonymously; hold 45‑min session; publish what was heard and actions. | D2: Start this quarter; quarterly
A3: Discussibility | B3: Hold problem-scenario discussions with anonymous voting and leader explanations. | C3: Use simple polls on 2–3 real dilemmas; record decisions and reasons; share notes. | D3: Start in 1–2 months; quarterly
A4: Discussibility | B4: Re‑introduce speak‑up channels and protections. | C4: One‑page guide + short video on where to report, what happens next, and non‑retaliation. | D4: Within 1 month; refresh twice a year
A5: Transparency | B5: Share a monthly ‘You said, we did’ update. | C5: 5‑bullet intranet/email note listing issues raised, actions taken, and any constraints. | D5: Monthly
A6: Transparency | B6: Publish answers to common employee questions. | C6: Collect questions (anonymous allowed), group them, and post clear answers in one place. | D6: Start within 1 month; update monthly
A7: Transparency | B7: Share short, visual guides for confusing processes. | C7: 1‑page flows for incident handling, promotions, and workload planning; include contacts. | D7: Draft in 4–6 weeks; review 6‑monthly
A8: Call someone to account | B8: Leaders run open reflection sessions on past decisions and learnings. | C8: 30‑min slot in team meetings; leader shares what worked/what didn’t and next changes. | D8: Start next month; quarterly
A9: Call someone to account | B9: Publish a simple ‘how to escalate’ guide. | C9: What to raise, when, to whom, expected timelines; include examples. | D9: Within 1 month
A10: Call someone to account | B10: Teams hold a monthly 20‑minute check‑in on promises and roadblocks. | C10: 3 questions: what did we commit, what’s blocked, what help is needed; record actions. | D10: Monthly
A11: Achievability | B11: Review targets to ensure they are realistic. | C11: Check workload, skills, resources; adjust targets or add support. | D11: Within 6 weeks; at planning cycles
A12: Achievability | B12: Map workloads every two months to spot overload. | C12: Simple RAG per person/team; drop, delay, or reassign low‑priority work. | D12: Every 2 months
... A25: Commitment | B25: Add culture metrics to leader scorecards and reviews. | C25: Track speak‑up usage, leader‑employee gap, and sentiment trend each quarter. | D25: Define in 4–6 weeks; quarterly
A26: Achievability | B26: Start ‘Workload Forecast Fridays’. | C26: Team predicts next week’s workload with R/Y/G tags; manager reallocates tasks as needed.
A27: Achievability | B27: Build a 30‑day skill booster for weak areas. | C27: L&D creates bite‑sized training for the 2 most common skill gaps; track completion and application.
A28: Achievability | B28: Introduce ‘Priority Swap Logs’. | C28: When a new task arrives, list which lower‑priority task will pause; share weekly.
A29: Achievability | B29: Create a monthly resourcing checkpoint. | C29: BU reviews capacity, backlog, and blockers with HR; temporarily redistribute resources.
A30: Call someone to account | B30: Add ‘Team Norm Reviews’ to monthly check‑ins. | C30: Teams rate themselves on 3 norms (ownership, honesty, follow‑through); manager summarizes 1 improvement action.
A31: Call someone to account | B31: Introduce micro‑escalation cards. | C31: Provide a card/listing of ‘what to escalate’, timelines, and the right role; share in all team meetings.
A32: Call someone to account | B32: Run 15‑min ‘Case Replay’ exercises. | C32: Manager picks a sanitized situation, explains what should have happened, and clarifies expectations.
A33: Call someone to account | B33: Launch quick ‘Stop/Start/Continue’ monthly peer feedback. | C33: Each member submits 1 behaviour under each category; manager consolidates themes anonymously.
A34: Clarity | B34: Publish ‘Role Boundaries Cheat Sheets’. | C34: One‑pager per role listing 5 decisions they can make and 5 they cannot; share yearly.
A35: Clarity | B35: Use ‘Fast FAQs’ for any new process. | C35: On launch, publish 5 FAQs + 5 Do’s/Don’ts; share in team chats.
A36: Clarity | B36: Standardize ‘Before you start’ checklists. | C36: Each process owner provides a quick checklist to verify prerequisites.
A37: Clarity | B37: Create cross‑BU walkthrough recordings. | C37: 10‑minute videos explaining steps, common confusions, and contacts; host on intranet.
... A57: Transparency | B57: Introduce ‘Why we changed this’ tags. | C57: Add a one‑line reason on each new process/policy update; keep it visible on the page.

Sheet Auto_Recommendations
A1: SoftControl | B1: AvgScore | C1: Risk_Level | D1: Recommendation | E1: How
A2: Role Modelling | B2: =VLOOKUP($A2,'SOFT CONTROL SCORECARD'!$A:$F,3,FALSE) -> 75 | C2: =VLOOKUP($A2,'SOFT CONTROL SCORECARD'!$A:$F,6,FALSE) -> Medium | D2: {=IF(OR($C2="Low",$C2="Medium"),_xlfn._xlws.FILTER(Recommendations!$B:$B,Recommendations!$A:$A=$A2),"No Recommendations – High Score")} -> Leaders share real examples of tough choices and lessons. | E2: {=IF(OR($C2="Low",$C2="Medium"),_xlfn._xlws.FILTER(Recommendations!$C:$C,Recommendations!$A:$A=$A2),"")} -> 10‑min segment at staff meetings or a short video; focus on what changed after mistakes.
D3: Let selected employees observe key meetings and debrief behaviours. | E3: 1 meeting/month; 15‑min debrief on listening, respect, and inviting challenge.
D4: Provide simple 360° behaviour feedback to leaders. | E4: 5–7 questions on listening, inclusion, inviting challenge; agree 2–3 actions.
D5: Start monthly ‘Leader Reality Checks’. | E5: Leaders visit one team (virtual/on‑site) for 20 min; ask 3 fixed questions; share learnings.
D6: Introduce ‘Show Your Work’ leadership notes. | E6: Leaders publish short notes after key decisions showing risks considered and trade‑offs.
D7: Set up a rotating leader Q&A carousel. | E7: Each month a different leader hosts a 15‑min open Q&A; anonymous submissions.
D8: Embed values moments in leader briefings. | E8: Leaders open each briefing with a 1‑minute story of a value demonstrated internally.
A9: Discussability | B9: =VLOOKUP($A9,'SOFT CONTROL SCORECARD'!$A:$F,3,FALSE) -> 78 | C9: =VLOOKUP($A9,'SOFT CONTROL SCORECARD'!$A:$F,6,FALSE) -> Medium | D9: {=IF(OR($C9="Low",$C9="Medium"),_xlfn._xlws.FILTER(Recommendations!$B:$B,Recommendations!$A:$A=$A9),"No Recommendations – High Score")} -> Start weekly ‘5‑Minute Clarity Checks’. | E9: {=IF(OR($C9="Low",$C9="Medium"),_xlfn._xlws.FILTER(Recommendations!$C:$C,Recommendations!$A:$A=$A9),"")} -> Managers ask 2 fixed prompts: ‘What’s unclear?’ and ‘Where did we hesitate last week?’; note 1 action and share in team chat.
D10: Introduce ‘anonymous dilemma slips’ in team meetings. | E10: Set up a quick QR form; manager picks 1 dilemma each week and explains how it would be handled; share guidance note.
D11: Run cross‑function mini‑panels every month. | E11: Bring 3 functions for a 20‑minute rapid‑fire Q&A on risk/ethics; record takeaways and distribute.
D12: Launch ‘What Would You Do?’ shorts. | E12: Upload a 60‑second case video bi‑weekly; employees vote on options; publish the correct escalation path.
A14: Achievability | B14: =VLOOKUP($A14,'SOFT CONTROL SCORECARD'!$A:$F,3,FALSE) -> 72 | C14: =VLOOKUP($A14,'SOFT CONTROL SCORECARD'!$A:$F,6,FALSE) -> Medium | D14: {=IF(OR($C14="Low",$C14="Medium"),_xlfn._xlws.FILTER(Recommendations!$B:$B,Recommendations!$A:$A=$A14),"No Recommendations – High Score")} -> Review targets to ensure they are realistic. | E14: {=IF(OR($C14="Low",$C14="Medium"),_xlfn._xlws.FILTER(Recommendations!$C:$C,Recommendations!$A:$A=$A14),"")} -> Check workload, skills, resources; adjust targets or add support.
D15: Map workloads every two months to spot overload. | E15: Simple RAG per person/team; drop, delay, or reassign low‑priority work.
D16: Add a short ‘pressure check’ to performance conversations. | E16: Ask about blockers, deadlines, support needed; note 1–2 actions.
D17: Start ‘Workload Forecast Fridays’. | E17: Team predicts next week’s workload with R/Y/G tags; manager reallocates tasks as needed.
D18: Build a 30‑day skill booster for weak areas. | E18: L&D creates bite‑sized training for the 2 most common skill gaps; track completion and application.
D19: Introduce ‘Priority Swap Logs’. | E19: When a new task arrives, list which lower‑priority task will pause; share weekly.
D20: Create a monthly resourcing checkpoint. | E20: BU reviews capacity, backlog, and blockers with HR; temporarily redistribute resources.
A21: Enforcement | B21: =VLOOKUP($A21,'SOFT CONTROL SCORECARD'!$A:$F,3,FALSE) -> 75 | C21: =VLOOKUP($A21,'SOFT CONTROL SCORECARD'!$A:$F,6,FALSE) -> Medium | D21: {=IF(OR($C21="Low",$C21="Medium"),_xlfn._xlws.FILTER(Recommendations!$B:$B,Recommendations!$A:$A=$A21),"No Recommendations – High Score")} -> Publish how misconduct or rule‑breaking is handled consistently. | E21: {=IF(OR($C21="Low",$C21="Medium"),_xlfn._xlws.FILTER(Recommendations!$C:$C,Recommendations!$A:$A=$A21),"")} -> Steps, roles, timelines, and example outcomes apply equally to all levels.
D22: Create a small network of trained ethics helpers. | E22: 1–2 per BU who can explain policies and direct people to the right channel.
D23: Send status updates to people who report concerns. | E23: Acknowledge receipt; share process and timelines; confirm closure (no sensitive details).
D24: Publish an internal ‘Consistent Consequences Grid’. | E24: Map behaviours to actions; share anonymized examples quarterly.
D25: Launch ‘Check‑in after closure’ protocol. | E25: After each resolved case, manager explains process (no names) and controls strengthened.
D26: Add SLA timers for case handling. | E26: Case system alerts when steps exceed defined timelines; monthly review for delays.
D27: Run a monthly enforcement alignment huddle. | E27: HR + Compliance review 3–4 recent cases to ensure decisions are consistent across functions.
A28: Clarity | B28: =VLOOKUP($A28,'SOFT CONTROL SCORECARD'!$A:$F,3,FALSE) -> 75 | C28: =VLOOKUP($A28,'SOFT CONTROL SCORECARD'!$A:$F,6,FALSE) -> Medium | D28: {=IF(OR($C28="Low",$C28="Medium"),_xlfn._xlws.FILTER(Recommendations!$B:$B,Recommendations!$A:$A=$A28),"No Recommendations – High Score")} -> Run team sessions to clarify who does what. | E28: {=IF(OR($C28="Low",$C28="Medium"),_xlfn._xlws.FILTER(Recommendations!$C:$C,Recommendations!$A:$A=$A28),"")} -> Create a simple responsibility map (RACI) and agree on handoffs.
D29: Publish a short guide on how common decisions are made. | E29: Who decides, inputs needed, timelines, and appeal/escalation path.
D30: Hold a monthly ‘ask anything’ hour with department heads. | E30: 45‑min session; allow anonymous questions; post a written summary.
D31: Publish ‘Role Boundaries Cheat Sheets’. | E31: One‑pager per role listing 5 decisions they can make and 5 they cannot; share yearly.
D32: Use ‘Fast FAQs’ for any new process. | E32: On launch, publish 5 FAQs + 5 Do’s/Don’ts; share in team chats.
D33: Standardize ‘Before you start’ checklists. | E33: Each process owner provides a quick checklist to verify prerequisites.
D34: Create cross‑BU walkthrough recordings. | E34: 10‑minute videos explaining steps, common confusions, and contacts; host on intranet.
A35: Transparency | B35: =VLOOKUP($A35,'SOFT CONTROL SCORECARD'!$A:$F,3,FALSE) -> 75 | C35: =VLOOKUP($A35,'SOFT CONTROL SCORECARD'!$A:$F,6,FALSE) -> Medium | D35: {=IF(OR($C35="Low",$C35="Medium"),_xlfn._xlws.FILTER(Recommendations!$B:$B,Recommendations!$A:$A=$A35),"No Recommendations – High Score")} -> Share a monthly ‘You said, we did’ update. | E35: {=IF(OR($C35="Low",$C35="Medium"),_xlfn._xlws.FILTER(Recommendations!$C:$C,Recommendations!$A:$A=$A35),"")} -> 5‑bullet intranet/email note listing issues raised, actions taken, and any constraints.
D36: Publish answers to common employee questions. | E36: Collect questions (anonymous allowed), group them, and post clear answers in one place.
D37: Share short, visual guides for confusing processes. | E37: 1‑page flows for incident handling, promotions, and workload planning; include contacts.
D38: Publish ‘This Month in Decisions’ micro‑updates. | E38: Bullet 5 key decisions (no names); add what changed for teams and link to updated docs.
D39: Create a simple ‘policy‑on‑a‑page’ hub. | E39: Convert key policies into 1‑page visuals; upload and tag; notify teams of monthly additions.
D40: Add quarterly ‘Open Data Hour’ sessions. | E40: BI team walks employees through dashboards (risks, trends, SLA metrics); take Q&A and publish summary.
D41: Introduce ‘Why we changed this’ tags. | E41: Add a one‑line reason on each new process/policy update; keep it visible on the page.
A42: Commitment | B42: =VLOOKUP($A42,'SOFT CONTROL SCORECARD'!$A:$F,3,FALSE) -> 74 | C42: =VLOOKUP($A42,'SOFT CONTROL SCORECARD'!$A:$F,6,FALSE) -> Medium | D42: {=IF(OR($C42="Low",$C42="Medium"),_xlfn._xlws.FILTER(Recommendations!$B:$B,Recommendations!$A:$A=$A42),"No Recommendations – High Score")} -> Publish a 6‑month culture plan with 3–5 actions and owners. | E42: {=IF(OR($C42="Low",$C42="Medium"),_xlfn._xlws.FILTER(Recommendations!$C:$C,Recommendations!$A:$A=$A42),"")} -> Define milestones; review progress at the executive meeting each month.
D43: Nominate culture champions across functions to keep actions moving. | E43: One‑page role; collect feedback; surface risks; share quick wins.
D44: Add culture metrics to leader scorecards and reviews. | E44: Track speak‑up usage, leader‑employee gap, and sentiment trend each quarter.
D45: Launch monthly ‘Purpose Moments’. | E45: Teams spend 5 minutes mapping current tasks to mission; share 1 example monthly.
D46: Start cross‑region ‘Culture Exchange Pods’. | E46: Groups of 6 from different markets meet monthly to share risks and practices; rotate facilitators.
D47: Introduce ‘Micro‑recognitions’ for values. | E47: Managers send 2 value‑based recognitions per month via collaboration tools; auto‑logged for performance.
D48: Hold quarterly ‘What’s Working Well’ share‑outs. | E48: Teams present 3 positive behaviours that improved collaboration or ethics; capture playbook items.
A49: Call someone to account | B49: =VLOOKUP($A49,'SOFT CONTROL SCORECARD'!$A:$F,3,FALSE) -> 70 | C49: =VLOOKUP($A49,'SOFT CONTROL SCORECARD'!$A:$F,6,FALSE) -> Medium | D49: {=IF(OR($C49="Low",$C49="Medium"),_xlfn._xlws.FILTER(Recommendations!$B:$B,Recommendations!$A:$A=$A49),"No Recommendations – High Score")} -> Leaders run open reflection sessions on past decisions and learnings. | E49: {=IF(OR($C49="Low",$C49="Medium"),_xlfn._xlws.FILTER(Recommendations!$C:$C,Recommendations!$A:$A=$A49),"")} -> 30‑min slot in team meetings; leader shares what worked/what didn’t and next changes.
D50: Publish a simple ‘how to escalate’ guide. | E50: What to raise, when, to whom, expected timelines; include examples.
D51: Teams hold a monthly 20‑minute check‑in on promises and roadblocks. | E51: 3 questions: what did we commit, what’s blocked, what help is needed; record actions.
D52: Add ‘Team Norm Reviews’ to monthly check‑ins. | E52: Teams rate themselves on 3 norms (ownership, honesty, follow‑through); manager summarizes 1 improvement action.
D53: Introduce micro‑escalation cards. | E53: Provide a card/listing of ‘what to escalate’, timelines, and the right role; share in all team meetings.
D54: Run 15‑min ‘Case Replay’ exercises. | E54: Manager picks a sanitized situation, explains what should have happened, and clarifies expectations.
D55: Launch quick ‘Stop/Start/Continue’ monthly peer feedback. | E55: Each member submits 1 behaviour under each category; manager consolidates themes anonymously.

Sheet AllResponses
A1: RespondentID | B1: QuestionID | C1: Question Text | D1: Response (user selects) | E1: Score_5 | F1: Score_100 | G1: SoftControl | H1: Response | I1: Scores | J1: FavorableFlag | K1: Dimensions | L1: Dimensions2
A2: R030 | B2: Q001 | C2: I believe that my Leaders and seniors are positive role models when it comes to successfully managing all potential risks | D2: Agree | E2: 4 | F2: 80 | G2: Role Modelling | L2: =_xlfn.XLOOKUP(AllResponses[[#This Row],[QuestionID]], FinalQuestions!$A:$A, FinalQuestions!$D:$D,"") -> Leadership Example‑Setting in Risk Management
A3: R030 | B3: Q002 | C3: All the executives set the right ‘tone at the top’ on the importance of managing all potential risks. | D3: Agree | E3: 4 | F3: 80 | G3: Role Modelling | L3: =_xlfn.XLOOKUP(AllResponses[[#This Row],[QuestionID]], FinalQuestions!$A:$A, FinalQuestions!$D:$D,"") -> Executive Commitment to Risk Culture
A4: R030 | B4: Q003 | C4: All the seniors encourage employees to identify, escalate and report all material potential risks in a timely manner | D4: Agree | E4: 4 | F4: 80 | G4: Role Modelling | L4: =_xlfn.XLOOKUP(AllResponses[[#This Row],[QuestionID]], FinalQuestions!$A:$A, FinalQuestions!$D:$D,"") -> Leadership Encouragement to Escalate Risks
A5: R030 | B5: Q004 | C5: When decisions are made by leaders, potential and long-term implications are usually considered. | D5: Agree | E5: 4 | F5: 80 | G5: Role Modelling | L5: =_xlfn.XLOOKUP(AllResponses[[#This Row],[QuestionID]], FinalQuestions!$A:$A, FinalQuestions!$D:$D,"") -> Long-Term Decision Awareness
A6: R030 | B6: Q005 | C6: In a Team or with leaders we can discuss openly when results fall short,and expectations aren’t met. | D6: Agree | E6: 4 | F6: 80 | G6: Discussability | L6: =_xlfn.XLOOKUP(AllResponses[[#This Row],[QuestionID]], FinalQuestions!$A:$A, FinalQuestions!$D:$D,"") -> Openness to Discussions
A7: R030 | B7: Q006 | C7: People can seek advice if they have questions about managing tasks or risks in the team. | D7: Agree | E7: 4 | F7: 80 | G7: Discussability | L7: =_xlfn.XLOOKUP(AllResponses[[#This Row],[QuestionID]], FinalQuestions!$A:$A, FinalQuestions!$D:$D,"") -> Access to Guidance
A8: R030 | B8: Q007 | C8: People feel comfortable sharing their opinion on work and risk management. | D8: Agree | E8: 4 | F8: 80 | G8: Discussability | L8: =_xlfn.XLOOKUP(AllResponses[[#This Row],[QuestionID]], FinalQuestions!$A:$A, FinalQuestions!$D:$D,"") -> Openness to Sharing Opinions
A9: R030 | B9: Q008 | C9: Within my team or department people feel comfortable to report risk management dillemas or if something goes wrong. | D9: Agree | E9: 4 | F9: 80 | G9: Discussability | L9: =_xlfn.XLOOKUP(AllResponses[[#This Row],[QuestionID]], FinalQuestions!$A:$A, FinalQuestions!$D:$D,"") -> Comfort in Reporting Risk Dilemmas
A10: R030 | B10: Q009 | C10: The amount of training in risk management I have received to help me manage risk in my job is sufficient. | D10: Agree | E10: 4 | F10: 80 | G10: Achievability | L10: =_xlfn.XLOOKUP(AllResponses[[#This Row],[QuestionID]], FinalQuestions!$A:$A, FinalQuestions!$D:$D,"") -> Adequacy of Risk Management Training
A11: R030 | B11: Q010 | C11: Within my team or department people have enough time and resources to do their job without taking unacceptable risks | D11: Agree | E11: 4 | F11: 80 | G11: Achievability | L11: =_xlfn.XLOOKUP(AllResponses[[#This Row],[QuestionID]], FinalQuestions!$A:$A, FinalQuestions!$D:$D,"") -> Workload Balance & Resource Sufficiency
A12: R030 | B12: Q011 | C12: People set targets that are achievable without compromising risk management policies, guidelines and procedures. | D12: Agree | E12: 4 | F12: 80 | G12: Achievability | L12: =_xlfn.XLOOKUP(AllResponses[[#This Row],[QuestionID]], FinalQuestions!$A:$A, FinalQuestions!$D:$D,"") -> Realistic Target Setting
A13: R030 | B13: Q012 | C13: People visibly consider potential risks when making strategic decisions | D13: Agree | E13: 4 | F13: 80 | G13: Achievability | L13: =_xlfn.XLOOKUP(AllResponses[[#This Row],[QuestionID]], FinalQuestions!$A:$A, FinalQuestions!$D:$D,"") -> Risk Insight in Decision Making
... A33: R030 | B33: Q032 | C33: Within my team at workplace, people are receptive to criticism on their own conduct. | D33: Strongly Agree | E33: 5 | F33: 100 | G33: Call someone to account | L33: =_xlfn.XLOOKUP(AllResponses[[#This Row],[QuestionID]], FinalQuestions!$A:$A, FinalQuestions!$D:$D,"") -> Consistency of Conduct Enforcement
A34: R030 | B34: 0 | C34: 0 | L34: =_xlfn.XLOOKUP(AllResponses[[#This Row],[QuestionID]], FinalQuestions!$A:$A, FinalQuestions!$D:$D,"")
A35: R001 | B35: Q001 | F35: 40 | G35: Role Modelling | H35: Disagree | I35: 2 | J35: 0 | K35: Leadership Example‑Setting in Risk Management | L35: =_xlfn.XLOOKUP(AllResponses[[#This Row],[QuestionID]], FinalQuestions!$A:$A, FinalQuestions!$D:$D,"") -> Leadership Example‑Setting in Risk Management
A36: R001 | B36: Q002 | F36: 40 | G36: Role Modelling | H36: Disagree | I36: 2 | J36: 0 | K36: Executive Commitment to Risk Culture | L36: =_xlfn.XLOOKUP(AllResponses[[#This Row],[QuestionID]], FinalQuestions!$A:$A, FinalQuestions!$D:$D,"") -> Executive Commitment to Risk Culture
A37: R001 | B37: Q003 | F37: 40 | G37: Role Modelling | H37: Disagree | I37: 2 | J37: 0 | K37: Leadership Encouragement to Escalate Risks | L37: =_xlfn.XLOOKUP(AllResponses[[#This Row],[QuestionID]], FinalQuestions!$A:$A, FinalQuestions!$D:$D,"") -> Leadership Encouragement to Escalate Risks
A38: R001 | B38: Q004 | F38: 40 | G38: Role Modelling | H38: Disagree | I38: 2 | J38: 0 | K38: Long-Term Decision Awareness | L38: =_xlfn.XLOOKUP(AllResponses[[#This Row],[QuestionID]], FinalQuestions!$A:$A, FinalQuestions!$D:$D,"") -> Long-Term Decision Awareness
A39: R001 | B39: Q005 | F39: 40 | G39: Discussability | H39: Disagree | I39: 2 | J39: 0 | K39: Openness to Discussions | L39: =_xlfn.XLOOKUP(AllResponses[[#This Row],[QuestionID]], FinalQuestions!$A:$A, FinalQuestions!$D:$D,"") -> Openness to Discussions
A40: R001 | B40: Q006 | F40: 40 | G40: Discussability | H40: Disagree | I40: 2 | J40: 0 | K40: Access to Guidance | L40: =_xlfn.XLOOKUP(AllResponses[[#This Row],[QuestionID]], FinalQuestions!$A:$A, FinalQuestions!$D:$D,"") -> Access to Guidance
A41: R001 | B41: Q007 | F41: 40 | G41: Discussability | H41: Disagree | I41: 2 | J41: 0 | K41: Openness to Sharing Opinions | L41: =_xlfn.XLOOKUP(AllResponses[[#This Row],[QuestionID]], FinalQuestions!$A:$A, FinalQuestions!$D:$D,"") -> Openness to Sharing Opinions
A42: R001 | B42: Q008 | F42: 40 | G42: Discussability | H42: Disagree | I42: 2 | J42: 0 | K42: Comfort in Reporting Risk Dilemmas | L42: =_xlfn.XLOOKUP(AllResponses[[#This Row],[QuestionID]], FinalQuestions!$A:$A, FinalQuestions!$D:$D,"") -> Comfort in Reporting Risk Dilemmas
A43: R001 | B43: Q009 | F43: 40 | G43: Achievability | H43: Disagree | I43: 2 | J43: 0 | K43: Adequacy of Risk Management Training | L43: =_xlfn.XLOOKUP(AllResponses[[#This Row],[QuestionID]], FinalQuestions!$A:$A, FinalQuestions!$D:$D,"") -> Adequacy of Risk Management Training
A44: R001 | B44: Q010 | F44: 40 | G44: Achievability | H44: Disagree | I44: 2 | J44: 0 | K44: Workload Balance & Resource Sufficiency | L44: =_xlfn.XLOOKUP(AllResponses[[#This Row],[QuestionID]], FinalQuestions!$A:$A, FinalQuestions!$D:$D,"") -> Workload Balance & Resource Sufficiency
A45: R001 | B45: Q011 | F45: 40 | G45: Achievability | H45: Disagree | I45: 2 | J45: 0 | K45: Realistic Target Setting | L45: =_xlfn.XLOOKUP(AllResponses[[#This Row],[QuestionID]], FinalQuestions!$A:$A, FinalQuestions!$D:$D,"") -> Realistic Target Setting
A46: R001 | B46: Q012 | F46: 40 | G46: Achievability | H46: Disagree | I46: 2 | J46: 0 | K46: Risk Insight in Decision Making | L46: =_xlfn.XLOOKUP(AllResponses[[#This Row],[QuestionID]], FinalQuestions!$A:$A, FinalQuestions!$D:$D,"") -> Risk Insight in Decision Making
... A866: R025 | B866: Q032 | F866: 80 | G866: Call someone to account | H866: Agree | I866: 4 | J866: 1 | K866: Openness to Receive Constructive Feedbacks | L866: =_xlfn.XLOOKUP(AllResponses[[#This Row],[QuestionID]], FinalQuestions!$A:$A, FinalQuestions!$D:$D,"") -> Consistency of Conduct Enforcement

Sheet Radar Chart
A1: SoftControl | B1: Score
A2: Role Modelling
A3: Discussability
A4: Achievability | B4: =IFERROR(ROUND(AVERAGEIF(Responses!$D:$D, 'SOFT CONTROL SCORECARD'!#REF!, Responses!$F:$F), 0), "")
A5: Enforcement | B5: =IFERROR(ROUND(AVERAGEIF(Responses!$D:$D, 'SOFT CONTROL SCORECARD'!#REF!, Responses!$F:$F), 0), "")
A6: Clarity | B6: =IFERROR(ROUND(AVERAGEIF(Responses!$D:$D, 'SOFT CONTROL SCORECARD'!#REF!, Responses!$F:$F), 0), "")
A7: Transparency | B7: =IFERROR(ROUND(AVERAGEIF(Responses!$D:$D, 'SOFT CONTROL SCORECARD'!#REF!, Responses!$F:$F), 0), "")
A8: Commitment | B8: =IFERROR(ROUND(AVERAGEIF(Responses!$D:$D, 'SOFT CONTROL SCORECARD'!#REF!, Responses!$F:$F), 0), "")
A9: Call Someone to Account | B9: =IFERROR(ROUND(AVERAGEIF(Responses!$D:$D, 'SOFT CONTROL SCORECARD'!#REF!, Responses!$F:$F), 0), "")
A33: SoftControl | B33: Low Risk | C33: Medium Risk | D33: High Risk | E33: Score
A34: Role Modelling | B34: =100 -> 100 | C34: =IF(OR('SOFT CONTROL SCORECARD'!$A2="Clarity",'SOFT CONTROL SCORECARD'!$A2="Role Modelling",'SOFT CONTROL SCORECARD'!$A2="Achievability"),80,70) -> 80 | D34: =IF(OR('SOFT CONTROL SCORECARD'!$A2="Clarity",'SOFT CONTROL SCORECARD'!$A2="Role Modelling",'SOFT CONTROL SCORECARD'!$A2="Achievability"), 70, 60) -> 70 | E34: =ROUND(IFERROR(AVERAGEIFS(Responses!$F:$F,Responses!$D:$D,$A2),0),0) -> 75
A35: Discussability | B35: =100 -> 100 | C35: =IF(OR('SOFT CONTROL SCORECARD'!$A3="Clarity",'SOFT CONTROL SCORECARD'!$A3="Role Modelling",'SOFT CONTROL SCORECARD'!$A3="Achievability"),80,70) -> 70 | D35: =IF(OR('SOFT CONTROL SCORECARD'!$A3="Clarity",'SOFT CONTROL SCORECARD'!$A3="Role Modelling",'SOFT CONTROL SCORECARD'!$A3="Achievability"), 70, 60) -> 60 | E35: =ROUND(IFERROR(AVERAGEIFS(Responses!$F:$F,Responses!$D:$D,$A3),0),0) -> 78
A36: Achievability | B36: =100 -> 100 | C36: =IF(OR('SOFT CONTROL SCORECARD'!$A4="Clarity",'SOFT CONTROL SCORECARD'!$A4="Role Modelling",'SOFT CONTROL SCORECARD'!$A4="Achievability"),80,70) -> 80 | D36: =IF(OR('SOFT CONTROL SCORECARD'!$A4="Clarity",'SOFT CONTROL SCORECARD'!$A4="Role Modelling",'SOFT CONTROL SCORECARD'!$A4="Achievability"), 70, 60) -> 70 | E36: =ROUND(IFERROR(AVERAGEIFS(Responses!$F:$F,Responses!$D:$D,$A4),0),0) -> 72
A37: Enforcement | B37: =100 -> 100 | C37: =IF(OR('SOFT CONTROL SCORECARD'!$A5="Clarity",'SOFT CONTROL SCORECARD'!$A5="Role Modelling",'SOFT CONTROL SCORECARD'!$A5="Achievability"),80,70) -> 70 | D37: =IF(OR('SOFT CONTROL SCORECARD'!$A5="Clarity",'SOFT CONTROL SCORECARD'!$A5="Role Modelling",'SOFT CONTROL SCORECARD'!$A5="Achievability"), 70, 60) -> 60 | E37: =ROUND(IFERROR(AVERAGEIFS(Responses!$F:$F,Responses!$D:$D,$A5),0),0) -> 75
A38: Clarity | B38: =100 -> 100 | C38: =IF(OR('SOFT CONTROL SCORECARD'!$A6="Clarity",'SOFT CONTROL SCORECARD'!$A6="Role Modelling",'SOFT CONTROL SCORECARD'!$A6="Achievability"),80,70) -> 80 | D38: =IF(OR('SOFT CONTROL SCORECARD'!$A6="Clarity",'SOFT CONTROL SCORECARD'!$A6="Role Modelling",'SOFT CONTROL SCORECARD'!$A6="Achievability"), 70, 60) -> 70 | E38: =ROUND(IFERROR(AVERAGEIFS(Responses!$F:$F,Responses!$D:$D,$A6),0),0) -> 75
A39: Transparency | B39: =100 -> 100 | C39: =IF(OR('SOFT CONTROL SCORECARD'!$A7="Clarity",'SOFT CONTROL SCORECARD'!$A7="Role Modelling",'SOFT CONTROL SCORECARD'!$A7="Achievability"),80,70) -> 70 | D39: =IF(OR('SOFT CONTROL SCORECARD'!$A7="Clarity",'SOFT CONTROL SCORECARD'!$A7="Role Modelling",'SOFT CONTROL SCORECARD'!$A7="Achievability"), 70, 60) -> 60 | E39: =ROUND(IFERROR(AVERAGEIFS(Responses!$F:$F,Responses!$D:$D,$A7),0),0) -> 75
A40: Commitment | B40: =100 -> 100 | C40: =IF(OR('SOFT CONTROL SCORECARD'!$A8="Clarity",'SOFT CONTROL SCORECARD'!$A8="Role Modelling",'SOFT CONTROL SCORECARD'!$A8="Achievability"),80,70) -> 70 | D40: =IF(OR('SOFT CONTROL SCORECARD'!$A8="Clarity",'SOFT CONTROL SCORECARD'!$A8="Role Modelling",'SOFT CONTROL SCORECARD'!$A8="Achievability"), 70, 60) -> 60 | E40: =ROUND(IFERROR(AVERAGEIFS(Responses!$F:$F,Responses!$D:$D,$A8),0),0) -> 74
A41: Call Someone to Account | B41: =100 -> 100 | C41: =IF(OR('SOFT CONTROL SCORECARD'!$A9="Clarity",'SOFT CONTROL SCORECARD'!$A9="Role Modelling",'SOFT CONTROL SCORECARD'!$A9="Achievability"),80,70) -> 70 | D41: =IF(OR('SOFT CONTROL SCORECARD'!$A9="Clarity",'SOFT CONTROL SCORECARD'!$A9="Role Modelling",'SOFT CONTROL SCORECARD'!$A9="Achievability"), 70, 60) -> 60 | E41: =ROUND(IFERROR(AVERAGEIFS(Responses!$F:$F,Responses!$D:$D,$A9),0),0) -> 70
